[{"id": "MFU000001", "desc": "5200N-3VD   UNIDAD GPS USADA", "unit": "PIEZA"}, {"id": "MFU000003", "desc": "B-64   BANDA DE MOTOR USADA", "unit": "PIEZA"}, {"id": "MFU000005", "desc": "47718   ABRAZADERA P/ TUBO USADA", "unit": "PIEZA"}, {"id": "MFU000006", "desc": "BCT290925310   BALARO C/ TAZA USADO", "unit": "PIEZA"}, {"id": "MFU000007", "desc": "59116155   BALERO USADO", "unit": "PIEZA"}, {"id": "MFU000008", "desc": "4TJM71421OPK   TAZA P/ BALERO USADA", "unit": "PIEZA"}, {"id": "MFU000009", "desc": "9415B   ESPEJO CONCAVO DE COFRE INTERNATIONAL USADO", "unit": "PIEZA"}, {"id": "MFU000010", "desc": "E11046328   ESPEJO CONCAVO LATERAL INTERNATIONAL USADO", "unit": "PIEZA"}, {"id": "MFU000011", "desc": "BALERO USADO C/ TAZA", "unit": "PIEZA"}, {"id": "MFU000012", "desc": "HM218210   TAZA DE BALERO USADA", "unit": "PIEZA"}, {"id": "MFU000013", "desc": "TBU0925002   TENSOR DE BANDA USADO", "unit": "PIEZA"}, {"id": "MFU000014", "desc": "E1892469   ESCUADRA P/ TRANSMISION EATON USADA", "unit": "PIEZA"}, {"id": "MFU000015", "desc": "MA0925011   MANGUERA ESPIRAL DE AIRE USADA", "unit": "PIEZA"}, {"id": "MFU000016", "desc": "133284F16431   SENSOR DE ACELERADOR USADO", "unit": "PIEZA"}, {"id": "MFU000017", "desc": "16400VK11B   BASE P/ FILTRO DE COMBUSTIBLE USADA", "unit": "PIEZA"}, {"id": "MFU000018", "desc": "CINTURON C/ AUTORESCATADOR", "unit": "PIEZA"}, {"id": "MFU000019", "desc": "EXK0925035   KIT DE EXTRACTORES USADOS (CAJA)", "unit": "PIEZA"}, {"id": "MFU000020", "desc": "BH011025320   BANDA HILUX USADA", "unit": "PIEZA"}, {"id": "MFU000022", "desc": "BT1049   BALATA TRASERA CAMIONETA USADA", "unit": "PIEZA"}, {"id": "MFU000023", "desc": "BG00863804U   LEVER DELANTERO USADO", "unit": "PIEZA"}, {"id": "MFU000024", "desc": "TR031025351   TORNILLO SANDVIK USADO", "unit": "PIEZA"}, {"id": "MFU000025", "desc": "CL160925064   CENTRALIZADOR DE JUMBO USADO", "unit": "PIEZA"}, {"id": "MFU000026", "desc": "FOCOS USADOS", "unit": "PIEZA"}, {"id": "MFU000027", "desc": "CU250925242   CARDA USADA", "unit": "PIEZA"}, {"id": "MFU000028", "desc": "4003905   BALANCIN DE MOTOR CUMMINS USADO", "unit": "PIEZA"}, {"id": "MFU000029", "desc": "4003903   BALANCIN DE MOTOR CUMMINS USADO", "unit": "PIEZA"}, {"id": "MFU000030", "desc": "F160925120   EJE DE BALANCINES (FLAUTA) USADO", "unit": "PIEZA"}, {"id": "MFU000031", "desc": "8929054   BALANCIN CAT C15 USADO", "unit": "PIEZA"}, {"id": "MFU000032", "desc": "3079661   SOPORTE DE BALANCIN CUMMINS USADO", "unit": "PIEZA"}, {"id": "MFU000033", "desc": "3079662   SOPORTE DE BALANCIN CUMMINS USADO", "unit": "PIEZA"}, {"id": "MFU000034", "desc": "3893584   SOPORTE DE BALANCIN CUMMINS USADO", "unit": "PIEZA"}, {"id": "MFU000035", "desc": "MC160925   CONJUNTO DE METALES DE CULATA USADOS", "unit": "PIEZA"}, {"id": "MFU000036", "desc": "B005265319858   MODULO ECM USADO 3579251C3", "unit": "PIEZA"}, {"id": "MFU000037", "desc": "4022914   SUJETADOR DE INYECTOR CUMMINS USADO", "unit": "PIEZA"}, {"id": "MFU000038", "desc": "5-2105   SOPORTE ALTERNADOR USADO", "unit": "PIEZA"}, {"id": "MFU000039", "desc": "680-243-015E   SOPORTE DE EJE USADO", "unit": "PIEZA"}, {"id": "MFU000040", "desc": "3581655C1   SOPORTE DE MOTOR INTERNATIONAL USADO", "unit": "PIEZA"}, {"id": "MFU000041", "desc": "3003026C1   SOPORTE USADO", "unit": "PIEZA"}, {"id": "MFU000042", "desc": "243-3020   SOPORTE ALTERNADOR R1600H USADO", "unit": "PIEZA"}, {"id": "MFU000043", "desc": "137-4981   SOPORTE DE ALTERNADOR R1600G USADO", "unit": "PIEZA"}, {"id": "MFU000044", "desc": "7K-6908   BASE DE ORUGA CAT USADA", "unit": "PIEZA"}, {"id": "MFU000045", "desc": "EB160925173   EJES BALANCIN CAT USADOS", "unit": "PIEZA"}, {"id": "MFU000046", "desc": "187-6549   INYECTOR CAT USADO", "unit": "PIEZA"}, {"id": "MFU000047", "desc": "1465A041   INYECTOR DENSO USADO", "unit": "PIEZA"}, {"id": "MFU000048", "desc": "MB4-16600   INYECTOR DENSO USADO", "unit": "PIEZA"}, {"id": "MFU000049", "desc": "IJN150925052   INYECTOR NISSAN USADO", "unit": "PIEZA"}, {"id": "MFU000050", "desc": "4220825   INYECTOR REMAN  USADO", "unit": "PIEZA"}, {"id": "MFU000060", "desc": "SK28P1294   INYECTOR USADO", "unit": "PIEZA"}, {"id": "MFU000061", "desc": "SK28P1296   INYECTOR USADO", "unit": "PIEZA"}, {"id": "MFU000062", "desc": "CN312027   INYECTOR USADO", "unit": "PIEZA"}, {"id": "MFU000063", "desc": "MU414460   INYECTOR USADO", "unit": "PIEZA"}, {"id": "MFU000064", "desc": "E003790   INYECTOR DE MOTOR 3711 CAT USADO", "unit": "PIEZA"}, {"id": "MFU000065", "desc": "20004295   BOMBA DE DIRECCIO IZQ. USADA", "unit": "PIEZA"}, {"id": "MFU000066", "desc": "LN160925177   LOCK NUT USADA", "unit": "PIEZA"}, {"id": "MFU000067", "desc": "V160925183   VALVULA DISTRIBUIDORA USADA", "unit": "PIEZA"}, {"id": "MFU000068", "desc": "478-7933-01   ECM CAT USADO", "unit": "PIEZA"}, {"id": "MFU000069", "desc": "28380632   MODULO CAT USADO", "unit": "PIEZA"}, {"id": "MFU000070", "desc": "145A212PR   LLANTA 145 A2 12PR USADA", "unit": "PIEZA"}, {"id": "MFU000071", "desc": "19575R16   LLANTA 195/75 R16 USADA", "unit": "PIEZA"}, {"id": "MFU000072", "desc": "RC250925267   RADIADOR HILUX C/ TOLVA USADO", "unit": "PIEZA"}, {"id": "MFU000073", "desc": "256111087207   ASIENTO DE VAN FORD USADO", "unit": "PIEZA"}, {"id": "MFU000074", "desc": "CTN-10   CONDENSADOR USADO", "unit": "PIEZA"}, {"id": "MFU000075", "desc": "3161904   FRENO DE MOTOR CUMMINS ISM USADO", "unit": "PIEZA"}, {"id": "MFU000076", "desc": "M250925267   MOCHILA P/ ACEITE HIDRAULICO USADA", "unit": "PIEZA"}, {"id": "MFU000079", "desc": "CD160925113   CAJA DE DIRECCION CAMION USADA", "unit": "PIEZA"}, {"id": "MFU000080", "desc": "FC200925230   FLECHA DIF TRASERO CAMIONETA USADA", "unit": "PIEZA"}, {"id": "MFU000081", "desc": "240313   HORQUILLA USADA", "unit": "PIEZA"}, {"id": "MFU000082", "desc": "N32B373   TRANSFER DELANTERO TOYOTA USADO", "unit": "PIEZA"}, {"id": "MFU000084", "desc": "8R3932 COLLET CAT USADO", "unit": "PIEZA"}, {"id": "MFU000085", "desc": "8R4267   COLLET USADO DE 4", "unit": "PIEZA"}, {"id": "MFU000086", "desc": "8R3937   COLLET USADO DE 4 1/2", "unit": "PIEZA"}, {"id": "MFU000087", "desc": "87R3938   COLLET USADO DE 5 1/2", "unit": "PIEZA"}, {"id": "MFU000088", "desc": "430-8922U   CRUCETA 430-8922 USADA", "unit": "PIEZA"}, {"id": "MFU000089", "desc": "221-8231   ENGRANE DE PLANETARIO USADO", "unit": "PIEZA"}, {"id": "MFU000090", "desc": "1V8033   PERNO DE SCOOP USADO I", "unit": "PIEZA"}, {"id": "MFU000091", "desc": "4V2122   PERNO SCOOP TRAM USADO", "unit": "PIEZA"}, {"id": "MFU000092", "desc": "730300675   YUGO DE 29 DIENTES C/ BALERO Y ENGRANE USADA", "unit": "PIEZA"}, {"id": "MFU000094", "desc": "344-7562   TAPA MOTOR C11 DAÐADA", "unit": "PIEZA"}, {"id": "MFU000095", "desc": "CIL250925273   CILINDRO LEVANTE CAMION USADO", "unit": "PIEZA"}, {"id": "MFU000096", "desc": "EC250925272   EJE DELANTERO DE CAMION USADO (SIN MAZAS)", "unit": "PIEZA"}, {"id": "MFU000097", "desc": "FC250925275   FLECHA CAMION USADA 39\"", "unit": "PIEZA"}, {"id": "MFU000098", "desc": "FC250925277   FLECHA CAMION USADA 66\"", "unit": "PIEZA"}, {"id": "MFU000099", "desc": "R17U   RIN DE 17\" USADO", "unit": "PIEZA"}, {"id": "MFU000104", "desc": "ABRU5   ABRAZADERA DE ESCAPE 458 USADA", "unit": "PIEZA"}, {"id": "MFU000105", "desc": "ABRCH314   ABRAZADERA DE ESCAPE TIPO CINCHO USADA", "unit": "PIEZA"}, {"id": "MFU000106", "desc": "EF-5705-10   FILTRO ACEITE USADO", "unit": "PIEZA"}, {"id": "MFU000107", "desc": "BP0925036   BUJE DE PLUMA JOHN DEERE USADO", "unit": "PIEZA"}, {"id": "MFU000108", "desc": "RESPIRADOR USADO", "unit": "PIEZA"}, {"id": "MFU000109", "desc": "46556   FILTRO AIRE USADO", "unit": "PIEZA"}, {"id": "MFU000110", "desc": "VHLX0925025   ABANICO HILUX USADO", "unit": "PIEZA"}, {"id": "MFU000111", "desc": "EHX0925026   ESPEJO DE HILUX USADO", "unit": "PIEZA"}, {"id": "MFU000112", "desc": "CR190925214   CORAZA HILUX USADA", "unit": "PIEZA"}, {"id": "MFU000113", "desc": "8D03   ACTUADOR DIFERENCIAL DELANTERO HILUX USADO", "unit": "PIEZA"}, {"id": "MFU000114", "desc": "85Y3   BRAZO EJE DELANTERO HILUX USADO", "unit": "PIEZA"}, {"id": "MFU000115", "desc": "HRT0925017   HORQUILLA DE SUSP INFERIOR IZQ. USADA", "unit": "PIEZA"}, {"id": "MFU000116", "desc": "TPM150925053   TAPA MAZA 8 BIRLOS VAN EXPRESS USADA", "unit": "PIEZA"}, {"id": "MFU000117", "desc": "DFF1509048   DISCO FRENOS DELANTERO FORD USADO B-0", "unit": "PIEZA"}, {"id": "MFU000119", "desc": "CU150925056   CALCE USADO", "unit": "PIEZA"}, {"id": "MFU000120", "desc": "466-7905   MODULO CAT USADO", "unit": "PIEZA"}, {"id": "MFU000121", "desc": "109-9437U   ARANDELA 12MM USADA", "unit": "PIEZA"}, {"id": "MFU000122", "desc": "137-8736   MOUNT USADO", "unit": "PIEZA"}, {"id": "MFU000123", "desc": "315-4412   ELECTROVALVULA USADA", "unit": "PIEZA"}, {"id": "MFU000124", "desc": "SS160925060   SEGURO USADO SANDVIK", "unit": "PIEZA"}, {"id": "MFU000125", "desc": "BA7226527   MODULO USADO", "unit": "PIEZA"}, {"id": "MFU000126", "desc": "TRC250925243   CAJA C/ TUERCAS USADAS DIFERENTES MEDIDAS", "unit": "PIEZA"}, {"id": "MFU000127", "desc": "BATERIA 31RP USADA", "unit": "PIEZA"}, {"id": "MFU000128", "desc": "3580026C1   MONTURA DE MUELLE USADA", "unit": "PIEZA"}, {"id": "MFU000129", "desc": "FD160925072   FLECHA DIFERENCIAL USADA L38 D46", "unit": "PIEZA"}, {"id": "MFU000130", "desc": "FD160925073   FLECHA DIFERENCIAL USADA L39 D41", "unit": "PIEZA"}, {"id": "MFU000131", "desc": "FD160925074   FLECHA DIFERENCIAL USADA L41 D24", "unit": "PIEZA"}, {"id": "MFU000132", "desc": "FD160925075   FLECHA DIFERENCIAL USADA L42 D36", "unit": "PIEZA"}, {"id": "MFU000133", "desc": "FD160925076   FLECHA DIFERENCIAL USADA L43 D41", "unit": "PIEZA"}, {"id": "MFU000134", "desc": "FD160925077   FLECHA DIFERENCIAL USADA L43 D42", "unit": "PIEZA"}, {"id": "MFU000135", "desc": "FD160925079   FLECHA DIFERENCIAL USADA L44 D46", "unit": "PIEZA"}, {"id": "MFU000136", "desc": "FD160925078   FLECHA DIFERENCIAL USADA L44 D47", "unit": "PIEZA"}, {"id": "MFU000137", "desc": "FD160925080   FLECHA DIFERENCIAL USADA L46 D33", "unit": "PIEZA"}, {"id": "MFU000138", "desc": "MANGUERA DE OXICORTE USADA", "unit": "PIEZA"}, {"id": "MFU000139", "desc": "TAPA DE TRANSMISION USADA", "unit": "PIEZA"}, {"id": "MFU000140", "desc": "CINTURON DE SEGURIDAD USADO", "unit": "PIEZA"}, {"id": "MFU000141", "desc": "ABRAZADERA DE MUELLE TOYOTA USADA", "unit": "PIEZA"}, {"id": "MFU000142", "desc": "ABRAZADERAS USADAS DIFERENTES MEDIDAS", "unit": "PIEZA"}, {"id": "MFU000143", "desc": "3370003BG RETEN DE MAZA USADO", "unit": "PIEZA"}, {"id": "MFU000144", "desc": "BOQUILLA DE OXICORTE C/ REGULADOR USADA", "unit": "PIEZA"}, {"id": "MFU000145", "desc": "APLICADOR DE SILICON USADO", "unit": "PIEZA"}, {"id": "MFU000146", "desc": "SOPORTE DE CABINA INTERNATIONAL USADO", "unit": "PIEZA"}, {"id": "MFU000147", "desc": "RESORTES USADOS", "unit": "PIEZA"}, {"id": "MFU000148", "desc": "RUEDA DE PLASTICO USADA", "unit": "PIEZA"}, {"id": "MFU000149", "desc": "P3103533 MODULO ECM USADO", "unit": "PIEZA"}, {"id": "MFU000150", "desc": "BANCO DE VALVULAS DE TRASNMISION PARA SCOOP", "unit": "PIEZA"}, {"id": "MFU000151", "desc": "VALVULA DE AVANCE DE JUMBO", "unit": "PIEZA"}, {"id": "MFU000152", "desc": "BOMBA DE DIRECCION DE CV", "unit": "PIEZA"}, {"id": "MFU000153", "desc": "MAZABALERO DE HILUX", "unit": "PIEZA"}, {"id": "MFU000154", "desc": "BOMBA DE TRANSMISION DE SCOOP", "unit": "PIEZA"}, {"id": "MFU000155", "desc": "TRANSMISION DE SCOOP R1600 (USADA)", "unit": "PIEZA"}, {"id": "MFU000156", "desc": "BOMBA 100 CC", "unit": "PIEZA"}, {"id": "MFU000157", "desc": "BALACIN (PESCADO) USADO", "unit": "PIEZA"}, {"id": "MFU000158", "desc": "ASIENTO DE JUMBO REPARADO/USADO", "unit": "PIEZA"}, {"id": "MFU000159", "desc": "CILINDRO DE AVANCE DE JUMBO SANDVIK REPARADO 55082949", "unit": "PIEZA"}, {"id": "MFU000161", "desc": "1906200 FLECHA DE ENTRE MODULOS (REPARADO)", "unit": "PIEZA"}, {"id": "MFU000162", "desc": "1869180 COLET USADO", "unit": "PIEZA"}, {"id": "MFU000163", "desc": "1869185 PERNO TORNO", "unit": "PIEZA"}, {"id": "MFU000164", "desc": "PUERTA DE CAMION USADA", "unit": "PIEZA"}, {"id": "MFU000165", "desc": "CODO DE AGUA PARA CV-155 USADO", "unit": "PIEZA"}, {"id": "MFU000166", "desc": "CAMISA P/ SCOOP TRAM USADA", "unit": "PIEZA"}, {"id": "MFU000167", "desc": "77020999 SHAFT", "unit": "PIEZA"}, {"id": "MFU000168", "desc": "CILINDRO DE RETRO REPARADO", "unit": "PIEZA"}, {"id": "MFU000169", "desc": "CAJA DE DIRECCION USADA", "unit": "PIEZA"}, {"id": "MFU000170", "desc": "FLECHA CARDAN ANC-02", "unit": "PIEZA"}, {"id": "MFU000171", "desc": "TAPAS DE POLEA DOBLE", "unit": "PIEZA"}, {"id": "MFU000172", "desc": "PERNO DE MONTURA RE-08", "unit": "PIEZA"}, {"id": "MFU000173", "desc": "CASQUILLOS DE PERNO RE-08", "unit": "PIEZA"}, {"id": "MFU000174", "desc": "PALANCA DE CAMBIO PARA JBO-10", "unit": "PIEZA"}, {"id": "MFU000175", "desc": "BOMBA DIRECCION CV-133", "unit": "PIEZA"}, {"id": "MFU000176", "desc": "BOTONERA P/LUCES", "unit": "PIEZA"}, {"id": "MFU000177", "desc": "DEPOSITO ACEITE HIDRAULICO", "unit": "PIEZA"}, {"id": "MFU000178", "desc": "DEPOSITO DE AGUA", "unit": "PIEZA"}, {"id": "MFU000179", "desc": "BISAGRAS DE CAJON", "unit": "PIEZA"}, {"id": "MFU000180", "desc": "PERNOS DEL GATO CV-110", "unit": "PIEZA"}, {"id": "MFU000181", "desc": "BRAZO VIAJERO CV-62", "unit": "PIEZA"}, {"id": "MFU000182", "desc": "BARRA DIRECCION CV-62", "unit": "PIEZA"}, {"id": "MFU000183", "desc": "SENSOR DE CLUTCH TA-01", "unit": "PIEZA"}, {"id": "MFU000184", "desc": "COMPUTADORA C11", "unit": "PIEZA"}, {"id": "MFU000185", "desc": "ASIENTO DE SCOOP USADO", "unit": "PIEZA"}, {"id": "MFU000186", "desc": "MANDO REPARADO ST-23 R1300", "unit": "PIEZA"}, {"id": "MFU000187", "desc": "VENTILADOR REPARADO", "unit": "PIEZA"}, {"id": "MFU000188", "desc": "85350239 ENFRIADOR DE ACEITE ( USADO )", "unit": "PIEZA"}, {"id": "MFU000189", "desc": "77006157 PLC (USADO)", "unit": "PIEZA"}, {"id": "MFU000190", "desc": "TURBO DE JUMBO/ANCLADOR (USADO)", "unit": "PIEZA"}, {"id": "MFU000191", "desc": "LAYNAS USADAS", "unit": "PIEZA"}, {"id": "MFU000192", "desc": "EJE TRASERO PARA SCOOP", "unit": "PIEZA"}, {"id": "MFU000193", "desc": "BOMBA PRINCIPAL", "unit": "PIEZA"}, {"id": "MFU000194", "desc": "JOYSTICK DE CAMBIOS", "unit": "PIEZA"}, {"id": "MFU000195", "desc": "ALTERNADOR KIOTI", "unit": "PIEZA"}, {"id": "MFU000196", "desc": "MOTOR LAVADORA", "unit": "PIEZA"}, {"id": "MFU000197", "desc": "6PK2425   BANDA DE MOTOR", "unit": "PIEZA"}, {"id": "MFU000198", "desc": "K080645   BANDA DE MOTOR", "unit": "PIEZA"}, {"id": "MFU000199", "desc": "A39   BANDA DE MOTOR", "unit": "PIEZA"}, {"id": "MFU000200", "desc": "K080694   BANDA DE MOTOR", "unit": "PIEZA"}, {"id": "MFU000201", "desc": "K060575   BANDA DE MOTOR", "unit": "PIEZA"}, {"id": "MFU000202", "desc": "B64   BANDA DE MOTOR USADA", "unit": "PIEZA"}, {"id": "MFU000203", "desc": "ABRAZADERA DE 4\"", "unit": "PIEZA"}, {"id": "MFU000204", "desc": "PLTN4   PLAFON LATERAL NARANJA 4", "unit": "PIEZA"}, {"id": "MFU000205", "desc": "PLN110925LED   PLAFON LATERAL NARANJA 5 C/ BISEL", "unit": "PIEZA"}, {"id": "MFU000206", "desc": "134734   POTENCIOMETRO 6 PINES 1697269C92", "unit": "PIEZA"}, {"id": "MFU000207", "desc": "21244697   RELEVADOR 12V VOLVO", "unit": "PIEZA"}, {"id": "MFU000208", "desc": "ABR3/8   ABRAZADERA DE 3/8", "unit": "PIEZA"}, {"id": "MFU000209", "desc": "BC300SS   ABRAZADERA DE ESCAPE 3\"", "unit": "PIEZA"}, {"id": "MFU000210", "desc": "ABRU5   ABRAZADERA DE ESCAPE 458 USADA", "unit": "PIEZA"}, {"id": "MFU000211", "desc": "742330117347   ABRAZADERA DE ESCAPE DONALDSON", "unit": "PIEZA"}, {"id": "MFU000212", "desc": "ABRCHN0925   ABRAZADERA DE ESCAPE TIPO CINCHO NUEVA", "unit": "PIEZA"}, {"id": "MFU000213", "desc": "ABRCH314   ABRAZADERA DE ESCAPE TIPO CINCHO USADA", "unit": "PIEZA"}, {"id": "MFU000214", "desc": "ABRT458   ABRAZADERA P/ TUBO 458", "unit": "PIEZA"}, {"id": "MFU000215", "desc": "500632   ABRAZADERA SIN FIN DE 5", "unit": "PIEZA"}, {"id": "MFU000216", "desc": "V2229   EMPAQUE DE TURBO", "unit": "PIEZA"}, {"id": "MFU000217", "desc": "3088984   EMPAQUE DE TURBO CUMMINS", "unit": "PIEZA"}, {"id": "MFU000218", "desc": "271500000000100174   MARCADOR DE PRESION DE ACEITE", "unit": "PIEZA"}, {"id": "MFU000219", "desc": "47718   ABRAZADERA P/ TUBO USADA", "unit": "PIEZA"}, {"id": "MFU000220", "desc": "12346   GOBERNADOR DE AIRE TKL275491", "unit": "PIEZA"}, {"id": "MFU000221", "desc": "72053136449   MANGUERA P/ TURBO 26204", "unit": "PIEZA"}, {"id": "MFU000222", "desc": "ACP103010   VALVULA DE RELEVO R14", "unit": "PIEZA"}, {"id": "MFU000223", "desc": "480059   VALVULA IPR MOTOR DT466", "unit": "PIEZA"}, {"id": "MFU000224", "desc": "TKL102626   VALVULA REGULADORA TKL102626", "unit": "PIEZA"}, {"id": "MFU000225", "desc": "TKL6909   VALVULA SELECTORA TKL6909", "unit": "PIEZA"}, {"id": "MFU000226", "desc": "CRU510XAUT   CRUCETA 281 MIXTA", "unit": "PIEZA"}, {"id": "MFU000227", "desc": "VCC271025   VARILLA COFRE DE CAMION", "unit": "PIEZA"}, {"id": "MFU000228", "desc": "BS12092025   BALLESTA DE SUSPENSIËN", "unit": "PIEZA"}, {"id": "MFU000229", "desc": "ACPQK1   KIT DE REPARACIËN DE FRENOS", "unit": "PIEZA"}, {"id": "MFU000230", "desc": "PR35IN   PASADOR ROSCADO DE 3 1/2", "unit": "PIEZA"}, {"id": "MFU000231", "desc": "4T37820   BALERO", "unit": "PIEZA"}, {"id": "MFU000232", "desc": "53893813936   BALERO C/ TAZA SET406", "unit": "PIEZA"}, {"id": "MFU000233", "desc": "538938139504   BALERO C/ TAZA SET413", "unit": "PIEZA"}, {"id": "MFU000234", "desc": "68063   BALERO GE30ES2RS", "unit": "PIEZA"}, {"id": "MFU000235", "desc": "53893591520   BALERO LM300811", "unit": "PIEZA"}, {"id": "MFU000236", "desc": "53893313566   BALERO LM48548", "unit": "PIEZA"}, {"id": "MFU000237", "desc": "53893650067   BALERO LM603011", "unit": "PIEZA"}, {"id": "MFU000238", "desc": "KTR12092025   KIT DE RETENES", "unit": "PIEZA"}, {"id": "MFU000239", "desc": "35066PRO   RETEN DE MAZA DELANTERO 35066PRO", "unit": "PIEZA"}, {"id": "MFU000240", "desc": "47697PRO   RETEN DE MAZA TRASERO 47697PRO", "unit": "PIEZA"}, {"id": "MFU000241", "desc": "4048V6   RETEN NATIONAL", "unit": "PIEZA"}, {"id": "MFU000242", "desc": "EE73140   RETEN YUGO DIFERENCIAL ROCKWELL", "unit": "PIEZA"}, {"id": "MFU000243", "desc": "PBM20080B   RONDANA P/SOPORTE DELANTERO MOTOR", "unit": "PIEZA"}, {"id": "MFU000244", "desc": "682034604685   SEAL 710072", "unit": "PIEZA"}, {"id": "MFU000245", "desc": "BCT290925310   BALARO C/ TAZA USADO", "unit": "PIEZA"}, {"id": "MFU000246", "desc": "59116155   BALERO USADO", "unit": "PIEZA"}, {"id": "MFU000247", "desc": "4TJM71421OPK   TAZA P/ BALERO USADA", "unit": "PIEZA"}, {"id": "MFU000248", "desc": "C21ESPEJHINPL007   ESPEJO CONVAVO COFRE INTERNATIONAL 4300", "unit": "PIEZA"}, {"id": "MFU000249", "desc": "31401241013   TUBO DE SUCCIËN TELESCOP═CO (2PZ)", "unit": "PIEZA"}, {"id": "MFU000250", "desc": "9415B   ESPEJO CONCAVO DE COFRE INTERNATIONAL USADO", "unit": "PIEZA"}, {"id": "MFU000251", "desc": "E11046328   ESPEJO CONCAVO LATERAL INTERNATIONAL USADO", "unit": "PIEZA"}, {"id": "MFU000252", "desc": "ACP64195   TAPA DE MAZA 3404195", "unit": "PIEZA"}, {"id": "MFU000253", "desc": "BALERO USADO C/ TAZA", "unit": "PIEZA"}, {"id": "MFU000254", "desc": "HM218210   TAZA DE BALERO USADA", "unit": "PIEZA"}, {"id": "MFU000255", "desc": "TBU0925002   TENSOR DE BANDA USADO", "unit": "PIEZA"}, {"id": "MFU000256", "desc": "ABR0925005   ABRAZADERA DE MUELLE", "unit": "PIEZA"}, {"id": "MFU000257", "desc": "MB0925007   METALES DE BIELA", "unit": "PIEZA"}, {"id": "MFU000258", "desc": "2040848C91   TAPON TANQUE DIESEL INTERNATIONAL", "unit": "PIEZA"}, {"id": "MFU000259", "desc": "E1892469   ESCUADRA P/ TRANSMISION EATON USADA", "unit": "PIEZA"}, {"id": "MFU000260", "desc": "EM0925010   EMPAQUE DE FLECHA LATERAL", "unit": "PIEZA"}, {"id": "MFU000261", "desc": "9908504   FANCLUTCH HORTON 9908504", "unit": "PIEZA"}, {"id": "MFU000262", "desc": "MA0925011   MANGUERA ESPIRAL DE AIRE USADA", "unit": "PIEZA"}, {"id": "MFU000263", "desc": "133284F16431   SENSOR DE ACELERADOR USADO", "unit": "PIEZA"}, {"id": "MFU000264", "desc": "BMI8   EMPAQUE METALICO", "unit": "PIEZA"}, {"id": "MFU000265", "desc": "BMI7   EMPAQUE METALICO", "unit": "PIEZA"}, {"id": "MFU000266", "desc": "CAV#2   HULE SOPORTE", "unit": "PIEZA"}, {"id": "MFU000267", "desc": "K200925227   KIT DE ARANDELAS DE COBRE", "unit": "PIEZA"}, {"id": "MFU000268", "desc": "PC150925058   CANDADO DE RUEDA", "unit": "PIEZA"}, {"id": "MFU000269", "desc": "55751624006   PLC EPIROC", "unit": "PIEZA"}, {"id": "MFU000270", "desc": "3370003BG RETEN DE MAZA USADO", "unit": "PIEZA"}, {"id": "MFU000271", "desc": "71407430   END PIECE", "unit": "PIEZA"}, {"id": "MFU000272", "desc": "70534225   PLATE", "unit": "PIEZA"}, {"id": "MFU000273", "desc": "70534279   PLATE", "unit": "PIEZA"}, {"id": "MFU000274", "desc": "SS160925060   SEGURO USADO SANDVIK", "unit": "PIEZA"}, {"id": "MFU000275", "desc": "SC0450627   BLOQUE DE HERRAMIENTAS P/ CUCHILLAS", "unit": "PIEZA"}, {"id": "MFU000276", "desc": "20016   COPLE P/ ZANCO", "unit": "PIEZA"}, {"id": "MFU000277", "desc": "77018896   DEUTZ DISPLAY", "unit": "PIEZA"}, {"id": "MFU000278", "desc": "721HR062   HOROMETRO", "unit": "PIEZA"}, {"id": "MFU000279", "desc": "55047602   JOYSTICK", "unit": "PIEZA"}, {"id": "MFU000280", "desc": "70690309   NUT", "unit": "PIEZA"}, {"id": "MFU000281", "desc": "BG01476904   PIN CLEVIS", "unit": "PIEZA"}, {"id": "MFU000282", "desc": "1458006   RELEVADOR DE 24V", "unit": "PIEZA"}, {"id": "MFU000283", "desc": "70700488   SCREW", "unit": "PIEZA"}, {"id": "MFU000284", "desc": "26438771   SPANDING SHAFT", "unit": "PIEZA"}, {"id": "MFU000285", "desc": "ST31160925   STRAP DE 31", "unit": "PIEZA"}, {"id": "MFU000286", "desc": "380073   CENTRALIZADOR DE ANCLADOR", "unit": "PIEZA"}, {"id": "MFU000287", "desc": "CN260925303   CONEXION A 90░ P/ MANGUERA #8", "unit": "PIEZA"}, {"id": "MFU000288", "desc": "MF370157   MANOMETRO", "unit": "PIEZA"}, {"id": "MFU000289", "desc": "73703023   SCREW", "unit": "PIEZA"}, {"id": "MFU000290", "desc": "20797408   BEARING BUSHING", "unit": "PIEZA"}, {"id": "MFU000291", "desc": "34571092   FLANGE", "unit": "PIEZA"}, {"id": "MFU000292", "desc": "26337508   FRAME STRIP", "unit": "PIEZA"}, {"id": "MFU000293", "desc": "57210240B17979333   GRASERA", "unit": "PIEZA"}, {"id": "MFU000294", "desc": "20020077   INTERNAL CIRCLIP", "unit": "PIEZA"}, {"id": "MFU000295", "desc": "6060012533   KIT DE EMPAQUES EPIROC", "unit": "PIEZA"}, {"id": "MFU000296", "desc": "BA7226527   MODULO USADO", "unit": "PIEZA"}, {"id": "MFU000297", "desc": "BT00002810   MORDAZA DE PLASTICO", "unit": "PIEZA"}, {"id": "MFU000298", "desc": "87345749   RETEN", "unit": "PIEZA"}, {"id": "MFU000299", "desc": "55155841   SEAL KIT", "unit": "PIEZA"}, {"id": "MFU000300", "desc": "85577709   SEAL KIT", "unit": "PIEZA"}, {"id": "MFU000301", "desc": "88472049   SEAL KIT", "unit": "PIEZA"}, {"id": "MFU000302", "desc": "TP031025351   TAPON DE VALVULA DE ACEITE", "unit": "PIEZA"}, {"id": "MFU000303", "desc": "AF03000036   WASHER LOCK PAIR", "unit": "PIEZA"}, {"id": "MFU000304", "desc": "BT0014068   BARLOCKING SANDVIK", "unit": "PIEZA"}, {"id": "MFU000305", "desc": "MD97017277   GUARDA SANDVIK", "unit": "PIEZA"}, {"id": "MFU000306", "desc": "XMLB500D2511   SENSOR DE PRESION ACEITE HIDRAULICO", "unit": "PIEZA"}, {"id": "MFU000307", "desc": "BG00376134   VALVE MAGNETIC", "unit": "PIEZA"}, {"id": "MFU000308", "desc": "LB082A8T   VALVULA HIDRAULICA", "unit": "PIEZA"}, {"id": "MFU000309", "desc": "ABRAZADERA P/ MANGUERAS HIDRAULICAS", "unit": "PIEZA"}, {"id": "MFU000310", "desc": "43040014   COPLE DE 2\"", "unit": "PIEZA"}, {"id": "MFU000311", "desc": "COPLE P/ BOMBA DE 100CC", "unit": "PIEZA"}, {"id": "MFU000312", "desc": "AR0925038   ARANDELA DE PERNO JOHN DEERE", "unit": "PIEZA"}, {"id": "MFU000313", "desc": "T362600   BUJE DE PLUMA JOHN DEERE", "unit": "PIEZA"}, {"id": "MFU000314", "desc": "BP0925036   BUJE DE PLUMA JOHN DEERE USADO", "unit": "PIEZA"}, {"id": "MFU000315", "desc": "T166715   BUJE JOHN DEERE", "unit": "PIEZA"}, {"id": "MFU000316", "desc": "T162582   BUJE JOHN DEERE", "unit": "PIEZA"}, {"id": "MFU000317", "desc": "T105988   CASQUILLO JOHN DEERE", "unit": "PIEZA"}, {"id": "MFU000318", "desc": "AT433550   FILTRO COMBUSTIBLE JOHN DEERE AT433550", "unit": "PIEZA"}, {"id": "MFU000319", "desc": "T162396   GRASERA JOHN DEERE", "unit": "PIEZA"}, {"id": "MFU000320", "desc": "DZ100211   INYECTOR P/ RETRO JOHN DEERE", "unit": "PIEZA"}, {"id": "MFU000321", "desc": "AT176538   PERNO DE PLUMA JOHN DEERE", "unit": "PIEZA"}, {"id": "MFU000322", "desc": "T185829   PERNO JOHN DEERE", "unit": "PIEZA"}, {"id": "MFU000323", "desc": "T159281   PERNO JOHN DEERE", "unit": "PIEZA"}, {"id": "MFU000324", "desc": "AT482071   PERNO JOHN DEERE", "unit": "PIEZA"}, {"id": "MFU000325", "desc": "AT448466   PERNO JOHN DEERE", "unit": "PIEZA"}, {"id": "MFU000326", "desc": "AT176537   PERNO JOHN DEERE", "unit": "PIEZA"}, {"id": "MFU000327", "desc": "AT176536   PERNO JOHN DEERE", "unit": "PIEZA"}, {"id": "MFU000328", "desc": "P160925182   PIN A", "unit": "PIEZA"}, {"id": "MFU000329", "desc": "U42446   PIN JOHN DEERE", "unit": "PIEZA"}, {"id": "MFU000330", "desc": "TC19663   RETEN JOHN DEERE TC19663", "unit": "PIEZA"}, {"id": "MFU000331", "desc": "40M7180   SEGURO JOHN DEERE", "unit": "PIEZA"}, {"id": "MFU000332", "desc": "T113128   TORNILLO HEXAGONAL 1 JOHN DEERE", "unit": "PIEZA"}, {"id": "MFU000333", "desc": "YZ501931   VALVULA SOLENOIDE 24V JOHN DEERE", "unit": "PIEZA"}, {"id": "MFU000334", "desc": "148100000000100423   CORTA CORRIENTE 1481000", "unit": "PIEZA"}, {"id": "MFU000335", "desc": "13443   CUARTO LUZ DIRECCIONAL IZQ. INTERNATIONAL 9200", "unit": "PIEZA"}, {"id": "MFU000336", "desc": "10628   FARO C/BISEL DER. INTERNATIONAL 9200", "unit": "PIEZA"}, {"id": "MFU000337", "desc": "272570000000100205   HOROMETRO 2725700", "unit": "PIEZA"}, {"id": "MFU000338", "desc": "3502062C1   PANEL DE SWITCH DE LUCES INTERNATIONAL 3502062C1", "unit": "PIEZA"}, {"id": "MFU000339", "desc": "5200N3VD   UNIDAD GPS USADA", "unit": "PIEZA"}, {"id": "MFU000340", "desc": "56870100000100549   BOCINA ELECTRICA TIPO DISCO", "unit": "PIEZA"}, {"id": "MFU000341", "desc": "201220000001000001   FOCO 1053 24V 2012000 (CAJA)", "unit": "PIEZA"}, {"id": "MFU000342", "desc": "201200000001000101   FOCO 1141 12V 2012000 (CAJA)", "unit": "PIEZA"}, {"id": "MFU000343", "desc": "200790000001000095   FOCO 2560 12V 2007900 (CAJA)", "unit": "PIEZA"}, {"id": "MFU000344", "desc": "195000000000100040   FOCO 9006 12V", "unit": "PIEZA"}, {"id": "MFU000345", "desc": "195230000000100045   FOCO 9007 12V", "unit": "PIEZA"}, {"id": "MFU000346", "desc": "822077471725   FOCO 9012 HALOGENO", "unit": "PIEZA"}, {"id": "MFU000347", "desc": "FCAF0925   FOCO AUXILIAR DE FARO", "unit": "PIEZA"}, {"id": "MFU000348", "desc": "PA66   FOCO DE 12V C/ BASE", "unit": "PIEZA"}, {"id": "MFU000349", "desc": "24VP21W   FOCO DE UN FILAMENTO", "unit": "PIEZA"}, {"id": "MFU000350", "desc": "196220000000100010   FOCO H3 24V", "unit": "PIEZA"}, {"id": "MFU000351", "desc": "197000000000100031   FOCO H4 12V", "unit": "PIEZA"}, {"id": "MFU000352", "desc": "197390000000100024   FOCO H9 12V", "unit": "PIEZA"}, {"id": "MFU000353", "desc": "PY21W   FOCO PY21W AMBAR", "unit": "PIEZA"}, {"id": "MFU000354", "desc": "FB60A16V   FUSIBLE 60 AMP 16 V", "unit": "PIEZA"}, {"id": "MFU000355", "desc": "20AMP   FUSIBLE DE 20 AMPERES", "unit": "PIEZA"}, {"id": "MFU000356", "desc": "SJFSAL250V   FUSIBLE DE VIDRIO", "unit": "PIEZA"}, {"id": "MFU000357", "desc": "IPR01   INTERRUPTOR PULSADOR ROJO", "unit": "PIEZA"}, {"id": "MFU000358", "desc": "3/4LED   PLAFON LED DE 3/4", "unit": "PIEZA"}, {"id": "MFU000359", "desc": "660731366501   PORTALAMPARA C/ CADENA", "unit": "PIEZA"}, {"id": "MFU000360", "desc": "F026T00063   RELEVADOR 24V", "unit": "PIEZA"}, {"id": "MFU000361", "desc": "145750000000100038   RELEVADOR UNIVERSAL 12V", "unit": "PIEZA"}, {"id": "MFU000362", "desc": "7502263604078   TIRA TIPO CHIP 5 LEDS (PAQUETE)", "unit": "PIEZA"}, {"id": "MFU000363", "desc": "AFX110925   ABRAZADERA P/ FARO AUXILIAR", "unit": "PIEZA"}, {"id": "MFU000364", "desc": "ABR1/2E   ABRAZADERA PARA INSTALACIËN ELECTRICA DE 1/2", "unit": "PIEZA"}, {"id": "MFU000365", "desc": "1870100000100244   ALARMA DE REVERSA", "unit": "PIEZA"}, {"id": "MFU000366", "desc": "9840645   CAJA CONDULET DE 1", "unit": "PIEZA"}, {"id": "MFU000367", "desc": "660731125528   CAUTIN TIPO LAPIZ", "unit": "PIEZA"}, {"id": "MFU000368", "desc": "MQCHA0001   CHALUPA GALVANIZADA", "unit": "PIEZA"}, {"id": "MFU000369", "desc": "378461   CONTACTO DE PARED ELECTRICO", "unit": "PIEZA"}, {"id": "MFU000370", "desc": "72170690   COPLE P/ INSTALACION ELECTRICA 1 1/4\"", "unit": "PIEZA"}, {"id": "MFU000371", "desc": "73746901   COPLE P/ INSTALACION ELECTRICA 1\"", "unit": "PIEZA"}, {"id": "MFU000372", "desc": "TK123A   COPLE P/ TUBO CONDUIT 1", "unit": "PIEZA"}, {"id": "MFU000373", "desc": "TBAL110925   TUBO DE ALUMINIO DE 1/4", "unit": "PIEZA"}, {"id": "MFU000374", "desc": "179995300000106120   FARO AUXILIAR CUADRADO", "unit": "PIEZA"}, {"id": "MFU000375", "desc": "DC12VOK   MICA ROJA DE TORRETA", "unit": "PIEZA"}, {"id": "MFU000376", "desc": "POV41/2LED   PLAFON LED DE 4 1/2 TRANSPARENTE", "unit": "PIEZA"}, {"id": "MFU000377", "desc": "POV36773BCK   PLAFON OVALADO LED TRANSPARENTE", "unit": "PIEZA"}, {"id": "MFU000378", "desc": "PRL271025   PLAFON REDONDO LED", "unit": "PIEZA"}, {"id": "MFU000379", "desc": "431000200000100734   UNIDAD SELLADA LED 431002", "unit": "PIEZA"}, {"id": "MFU000380", "desc": "S80 ENCHUFE DE ANGULO UNIVERSAL", "unit": "PIEZA"}, {"id": "MFU000381", "desc": "FL21005F REFLECTOR LED 50 WATTS", "unit": "PIEZA"}, {"id": "MFU000382", "desc": "9840010 CAJA RECTANGULAR DE ALUMINIO P/ CONTACTO ELECTRICO", "unit": "PIEZA"}, {"id": "MFU000383", "desc": "4867 ENCHUFE ELECTRICO", "unit": "PIEZA"}, {"id": "MFU000384", "desc": "179995300000106120   FARO AUXILIAR CUADRADO", "unit": "PIEZA"}, {"id": "MFU000385", "desc": "CAJA DE TERMINALES ELECTRICAS", "unit": "PIEZA"}, {"id": "MFU000386", "desc": "CONEXIËN A 45░ CARA PLANA #4 TUERCA 1/4", "unit": "PIEZA"}, {"id": "MFU000387", "desc": "CONEXIËN A 90░ CARA PLANA #12 TUERCA 15/16", "unit": "PIEZA"}, {"id": "MFU000388", "desc": "CONEXIËN A 90░ CONICA #4 TUERCA 1/4", "unit": "PIEZA"}, {"id": "MFU000389", "desc": "CONEXIËN A 90░ CONICA #4 TUERCA 1/8", "unit": "PIEZA"}, {"id": "MFU000390", "desc": "CONEXIËN A 90░ CONICA #6 TUERCA 3/8", "unit": "PIEZA"}, {"id": "MFU000391", "desc": "CONEXIËN RECTA CONICA #12TUERCA 15/16", "unit": "PIEZA"}, {"id": "MFU000392", "desc": "CONEXIËN RECTA CONICA #6 TUERCA 3/8", "unit": "PIEZA"}, {"id": "MFU000393", "desc": "CONEXIËN A 90░ CONICA #16 TUERCA DE 1\"", "unit": "PIEZA"}, {"id": "MFU000394", "desc": "10MJ10BKHD   PASAMUROS #10", "unit": "PIEZA"}, {"id": "MFU000395", "desc": "12MB12MJ   PASAMUROS #12", "unit": "PIEZA"}, {"id": "MFU000396", "desc": "16MJ16BKHD   PASAMUROS #16", "unit": "PIEZA"}, {"id": "MFU000397", "desc": "4MJ4BKHD   PASAMUROS #4", "unit": "PIEZA"}, {"id": "MFU000398", "desc": "10LNCFU   TUERCA P/ CONEXIËN HIDRAULICA #10", "unit": "PIEZA"}, {"id": "MFU000399", "desc": "12LNCFU   TUERCA P/ CONEXIËN HIDRAULICA #12", "unit": "PIEZA"}, {"id": "MFU000400", "desc": "16LNCFU   TUERCA P/ CONEXIËN HIDRAULICA #16", "unit": "PIEZA"}, {"id": "MFU000401", "desc": "6LN530   TUERCA P/ CONEXIËN HIDRAULICA #6", "unit": "PIEZA"}, {"id": "MFU000402", "desc": "M0350010   CASQUILLO P/ CONEXIËN HIDRAULICA #10", "unit": "PIEZA"}, {"id": "MFU000403", "desc": "M0350012   CASQUILLO P/ CONEXIËN HIDRAULICA #12", "unit": "PIEZA"}, {"id": "MFU000404", "desc": "M0350016   CASQUILLO P/ CONEXIËN HIDRAULICA #16", "unit": "PIEZA"}, {"id": "MFU000405", "desc": "CONEXIËN RECTA CARA PLANA #12 TUERCA 15/16", "unit": "PIEZA"}, {"id": "MFU000406", "desc": "M224931212   FERULA A 90░ CARA PLANA #12 TUERCA 15/16", "unit": "PIEZA"}, {"id": "MFU000407", "desc": "M225121010   FERULA P/ CONEXIËN HIDRAULICA #10 TUERCA 5/8", "unit": "PIEZA"}, {"id": "MFU000408", "desc": "M225121616   FERULA P/ CONEXIËN HIDRAULICA #16 TUERCA DE 1\"", "unit": "PIEZA"}, {"id": "MFU000409", "desc": "M0340004   CASQUILLO P/ CONEXIËN HIDRAULICA #4", "unit": "PIEZA"}, {"id": "MFU000410", "desc": "M0345008   CASQUILLO P/ CONEXIËN HIDRAULICA #8", "unit": "PIEZA"}, {"id": "MFU000411", "desc": "CONEXIËN A 45░ CARA PLANA #6 TUERCA 3/8", "unit": "PIEZA"}, {"id": "MFU000412", "desc": "CONEXIËN A 45░ CARA PLANA #8 TUERCA 1/2", "unit": "PIEZA"}, {"id": "MFU000413", "desc": "CONEXIËN A 90░ CARA PLANA #6 TUERCA 3/8", "unit": "PIEZA"}, {"id": "MFU000414", "desc": "CONEXIËN A 90░ CARA PLANA #8 TUERCA 1/2", "unit": "PIEZA"}, {"id": "MFU000415", "desc": "CONEXIËN A 90░ CONICA #6 TUERCA 1/4", "unit": "PIEZA"}, {"id": "MFU000416", "desc": "CONEXIËN RECTA CARA PLANA #6 TUERCA 3/8", "unit": "PIEZA"}, {"id": "MFU000417", "desc": "CONEXIËN RECTA CARA PLANA #8 TUERCA 1/2", "unit": "PIEZA"}, {"id": "MFU000418", "desc": "CONEXIËN RECTA CONICA #4 TUERCA 1/4", "unit": "PIEZA"}, {"id": "MFU000419", "desc": "CONEXIËN RECTA CONICA #4 TUERCA 1/8", "unit": "PIEZA"}, {"id": "MFU000420", "desc": "CONEXIËN RECTA CONICA #6 TUERCA 1/4", "unit": "PIEZA"}, {"id": "MFU000421", "desc": "CONEXIËN RECTA CONICA #8 TUERC A 3/8", "unit": "PIEZA"}, {"id": "MFU000422", "desc": "M225120808   FERULA P/ CONEXIËN HIDRAULICA #8 TUERCA 1/2", "unit": "PIEZA"}, {"id": "MFU000423", "desc": "12EST58   MANGUERA #10", "unit": "PIEZA"}, {"id": "MFU000424", "desc": "12EST34   MANGUERA #12", "unit": "PIEZA"}, {"id": "MFU000425", "desc": "12EST1   MANGUERA #16", "unit": "PIEZA"}, {"id": "MFU000426", "desc": "2SN14   MANGUERA #4", "unit": "PIEZA"}, {"id": "MFU000427", "desc": "2GIC14C/39   MANGUERA GORILLA DE 1\"", "unit": "PIEZA"}, {"id": "MFU000428", "desc": "EX1509045   EXTINTOR DE 9 KG", "unit": "PIEZA"}, {"id": "MFU000429", "desc": "MG30925044   MANGUERA AZUL DE 3\"", "unit": "PIEZA"}, {"id": "MFU000430", "desc": "COT11/2   MANGUERA CORRUGADA 1 1/2\"", "unit": "PIEZA"}, {"id": "MFU000431", "desc": "COT1   MANGUERA CORRUGADA 1\"", "unit": "PIEZA"}, {"id": "MFU000432", "desc": "COT1/2   MANGUERA CORRUGADA 1/2\"", "unit": "PIEZA"}, {"id": "MFU000433", "desc": "COT3/4   MANGUERA CORRUGADA 3/4\"", "unit": "PIEZA"}, {"id": "MFU000434", "desc": "MANGUERA DE OXICORTE USADA", "unit": "PIEZA"}, {"id": "MFU000435", "desc": "47533   NIPLE GALVANIZADO DE 1 X 4", "unit": "PIEZA"}, {"id": "MFU000436", "desc": "NIPLE GALVANIZADO DE 1 X 3", "unit": "PIEZA"}, {"id": "MFU000437", "desc": "TEE1250925236   TEE GALVANIZADA DE 1", "unit": "PIEZA"}, {"id": "MFU000438", "desc": "372381   CATERPILLAR KIT SEAL 4958179", "unit": "PIEZA"}, {"id": "MFU000439", "desc": "6L9589   EMPAQUE", "unit": "PIEZA"}, {"id": "MFU000440", "desc": "1478218   INSERT SEAT", "unit": "PIEZA"}, {"id": "MFU000441", "desc": "7Y1884   JP RING", "unit": "PIEZA"}, {"id": "MFU000442", "desc": "UKM79P   O RING", "unit": "PIEZA"}, {"id": "MFU000443", "desc": "1P3707   ORING", "unit": "PIEZA"}, {"id": "MFU000444", "desc": "1P3706   ORING C", "unit": "PIEZA"}, {"id": "MFU000445", "desc": "931509   RING BACK", "unit": "PIEZA"}, {"id": "MFU000446", "desc": "G000JSDL5S2106   SEAL", "unit": "PIEZA"}, {"id": "MFU000447", "desc": "8G4190   SEAL A", "unit": "PIEZA"}, {"id": "MFU000448", "desc": "5P2671   SEAL CAT", "unit": "PIEZA"}, {"id": "MFU000449", "desc": "CATAAUS2457339   SEAL GPCSHA", "unit": "PIEZA"}, {"id": "MFU000450", "desc": "2352484   SEAL LIP TYPE", "unit": "PIEZA"}, {"id": "MFU000451", "desc": "1090076   SEAL O RING", "unit": "PIEZA"}, {"id": "MFU000452", "desc": "1090078   SEAL O RING", "unit": "PIEZA"}, {"id": "MFU000453", "desc": "9F4446   SEAL O RING", "unit": "PIEZA"}, {"id": "MFU000454", "desc": "3S9643   SEAL OIL", "unit": "PIEZA"}, {"id": "MFU000455", "desc": "2P1692   SEAL ORING", "unit": "PIEZA"}, {"id": "MFU000456", "desc": "2U5388   SEAL V R", "unit": "PIEZA"}, {"id": "MFU000457", "desc": "1P3700   SELLO RECTANGULAR", "unit": "PIEZA"}, {"id": "MFU000458", "desc": "1515928   TUBE ASOIL", "unit": "PIEZA"}, {"id": "MFU000459", "desc": "8G4945   TW SEAL A", "unit": "PIEZA"}, {"id": "MFU000460", "desc": "3577540   VALVEFIL", "unit": "PIEZA"}, {"id": "MFU000461", "desc": "4W8926   WASHER", "unit": "PIEZA"}, {"id": "MFU000462", "desc": "20553299   ANRANDELA 5P8244", "unit": "PIEZA"}, {"id": "MFU000463", "desc": "1868239   BUNG", "unit": "PIEZA"}, {"id": "MFU000464", "desc": "1S4295   EMPAQUE", "unit": "PIEZA"}, {"id": "MFU000465", "desc": "5P8334   FITTING", "unit": "PIEZA"}, {"id": "MFU000466", "desc": "2746851   GASKETTURBO", "unit": "PIEZA"}, {"id": "MFU000467", "desc": "3B8489   GRASERA", "unit": "PIEZA"}, {"id": "MFU000468", "desc": "1478218   INSERT SEAT", "unit": "PIEZA"}, {"id": "MFU000469", "desc": "639850   ISOLATOR PAN", "unit": "PIEZA"}, {"id": "MFU000470", "desc": "3711607   PLATE", "unit": "PIEZA"}, {"id": "MFU000471", "desc": "5M6213   PLUG 5M6213", "unit": "PIEZA"}, {"id": "MFU000472", "desc": "8K6464   RING", "unit": "PIEZA"}, {"id": "MFU000473", "desc": "2124331   SENSOR", "unit": "PIEZA"}, {"id": "MFU000474", "desc": "1087638   SPACER", "unit": "PIEZA"}, {"id": "MFU000475", "desc": "4445305   SPRING", "unit": "PIEZA"}, {"id": "MFU000476", "desc": "2773076   TUBE ASOIL", "unit": "PIEZA"}, {"id": "MFU000477", "desc": "9S8010   US PLUG", "unit": "PIEZA"}, {"id": "MFU000478", "desc": "1972474   VALVE AS", "unit": "PIEZA"}, {"id": "MFU000479", "desc": "5P8247   WASHER", "unit": "PIEZA"}, {"id": "MFU000480", "desc": "91261757MX   WASHER", "unit": "PIEZA"}, {"id": "MFU000481", "desc": "6V2360   WASHER", "unit": "PIEZA"}, {"id": "MFU000482", "desc": "2094579   ABRAZADERA", "unit": "PIEZA"}, {"id": "MFU000483", "desc": "1217958   BOLTMTG", "unit": "PIEZA"}, {"id": "MFU000484", "desc": "1869697   BUSBAR AS", "unit": "PIEZA"}, {"id": "MFU000485", "desc": "8M9PR5   EMPAQUE", "unit": "PIEZA"}, {"id": "MFU000486", "desc": "1299452   GASKET", "unit": "PIEZA"}, {"id": "MFU000487", "desc": "331410155   KIT ORINGS", "unit": "PIEZA"}, {"id": "MFU000488", "desc": "1956283   NUTSQUARE", "unit": "PIEZA"}, {"id": "MFU000489", "desc": "7T8890   PUMP A", "unit": "PIEZA"}, {"id": "MFU000490", "desc": "13N8506   RING", "unit": "PIEZA"}, {"id": "MFU000491", "desc": "EOS3305   SEAL", "unit": "PIEZA"}, {"id": "MFU000492", "desc": "392013   SEAL VALVE", "unit": "PIEZA"}, {"id": "MFU000493", "desc": "4309455   SENSOR GP", "unit": "PIEZA"}, {"id": "MFU000494", "desc": "3056873   SENSOR GPPR", "unit": "PIEZA"}, {"id": "MFU000495", "desc": "1745643   SPACER", "unit": "PIEZA"}, {"id": "MFU000496", "desc": "2485513   TERMOSTATO", "unit": "PIEZA"}, {"id": "MFU000497", "desc": "10R3147   INJGP FUEL", "unit": "PIEZA"}, {"id": "MFU000498", "desc": "P11E3FA46   INYECTOR P/ RETRO CAT", "unit": "PIEZA"}, {"id": "MFU000499", "desc": "6I2431   SEAL END TANK", "unit": "PIEZA"}, {"id": "MFU000500", "desc": "1425867   SEAL GP", "unit": "PIEZA"}, {"id": "MFU000501", "desc": "3181179   SENSOR", "unit": "PIEZA"}, {"id": "MFU000502", "desc": "4928593   SENSOR", "unit": "PIEZA"}, {"id": "MFU000503", "desc": "1868784   SPACER", "unit": "PIEZA"}, {"id": "MFU000504", "desc": "1126174   SWITCH A", "unit": "PIEZA"}, {"id": "MFU000505", "desc": "5R7276   BANDA DE CAUCHO P/R1600", "unit": "PIEZA"}, {"id": "MFU000506", "desc": "2173673   EMPAQUE DE CARTER", "unit": "PIEZA"}, {"id": "MFU000507", "desc": "2295711   SEAL ISOLATI", "unit": "PIEZA"}, {"id": "MFU000508", "desc": "1V5635   BUJE DE METAL", "unit": "PIEZA"}, {"id": "MFU000509", "desc": "2M0344   EMPAQUE DE HULE", "unit": "PIEZA"}, {"id": "MFU000510", "desc": "9G5315   JUEGO DE SELLOS", "unit": "PIEZA"}, {"id": "MFU000511", "desc": "7K9220   RETEN", "unit": "PIEZA"}, {"id": "MFU000512", "desc": "7X2623   RING", "unit": "PIEZA"}, {"id": "MFU000513", "desc": "1869394   SHIM", "unit": "PIEZA"}, {"id": "MFU000514", "desc": "1869393   CALCE", "unit": "PIEZA"}, {"id": "MFU000515", "desc": "1635522   SHIM", "unit": "PIEZA"}, {"id": "MFU000516", "desc": "1635521   SHIM", "unit": "PIEZA"}, {"id": "MFU000517", "desc": "2K4160   ARANDELA", "unit": "PIEZA"}, {"id": "MFU000518", "desc": "1099437   ARANDELA 12MM", "unit": "PIEZA"}, {"id": "MFU000519", "desc": "2346682   BOLT12 POIN", "unit": "PIEZA"}, {"id": "MFU000520", "desc": "2024086   JUEGO DE EMPAQUES", "unit": "PIEZA"}, {"id": "MFU000521", "desc": "1398737   MOUNT", "unit": "PIEZA"}, {"id": "MFU000522", "desc": "1398736   MOUNT", "unit": "PIEZA"}, {"id": "MFU000523", "desc": "6V1250   ORING", "unit": "PIEZA"}, {"id": "MFU000524", "desc": "9Y9895   SEAL GP CRANK", "unit": "PIEZA"}, {"id": "MFU000525", "desc": "3K9770   TUERCA", "unit": "PIEZA"}, {"id": "MFU000526", "desc": "8T0319   ARM A", "unit": "PIEZA"}, {"id": "MFU000527", "desc": "6V8658   ARM A", "unit": "PIEZA"}, {"id": "MFU000528", "desc": "6V5849   BLADE A", "unit": "PIEZA"}, {"id": "MFU000529", "desc": "CATAAES1285040   BLADE A", "unit": "PIEZA"}, {"id": "MFU000530", "desc": "CATAACN1869177   PISTON", "unit": "PIEZA"}, {"id": "MFU000531", "desc": "CATAAFR1132529   BOOT CAT", "unit": "PIEZA"}, {"id": "MFU000532", "desc": "2B7559   CORK CAT", "unit": "PIEZA"}, {"id": "MFU000533", "desc": "CATAAE 1192876   HOSE COOLING CAT", "unit": "PIEZA"}, {"id": "MFU000534", "desc": "1656593   LATCH AS", "unit": "PIEZA"}, {"id": "MFU000535", "desc": "CATAA  0975144   O RING CAT", "unit": "PIEZA"}, {"id": "MFU000536", "desc": "2144332   PLUG CAT", "unit": "PIEZA"}, {"id": "MFU000537", "desc": "975174   RING CAT", "unit": "PIEZA"}, {"id": "MFU000538", "desc": "CATAAIT010975175   RING CAT", "unit": "PIEZA"}, {"id": "MFU000539", "desc": "CATAAIT 8I3852   SEALOR", "unit": "PIEZA"}, {"id": "MFU000540", "desc": "5BE   TORNILLO CAT 5BE", "unit": "PIEZA"}, {"id": "MFU000541", "desc": "4660406045   COVER BOMBA INYECCION", "unit": "PIEZA"}, {"id": "MFU000542", "desc": "2V7153   SPIDER", "unit": "PIEZA"}, {"id": "MFU000543", "desc": "4308922   UNIV JOINT (CRUCETA)", "unit": "PIEZA"}, {"id": "MFU000544", "desc": "5P7470   ABRAZADERA DE MANGUERA SUPERIOR", "unit": "PIEZA"}, {"id": "MFU000545", "desc": "4V5234   ARANDELA", "unit": "PIEZA"}, {"id": "MFU000546", "desc": "6V1882   CONE", "unit": "PIEZA"}, {"id": "MFU000547", "desc": "4F2041   CUP BEARING", "unit": "PIEZA"}, {"id": "MFU000548", "desc": "4J0526   O RING", "unit": "PIEZA"}, {"id": "MFU000549", "desc": "7M8485   ORING", "unit": "PIEZA"}, {"id": "MFU000550", "desc": "9X7743   RETEN CAT", "unit": "PIEZA"}, {"id": "MFU000551", "desc": "3004545   ROLLER GP", "unit": "PIEZA"}, {"id": "MFU000552", "desc": "4391590   ACOPLADOR HEMBRA DE DESCONEXION RAPIDA", "unit": "PIEZA"}, {"id": "MFU000553", "desc": "4391591   BOQUILLA MACHO DE DESCONEXIËN RAPIDA", "unit": "PIEZA"}, {"id": "MFU000554", "desc": "3793436   ENFRIADOR DE ACEITE CORE AS", "unit": "PIEZA"}, {"id": "MFU000555", "desc": "4710998   TAPËN DE CONEXIËN HIDRAULICA", "unit": "PIEZA"}, {"id": "MFU000556", "desc": "4710997   TAPËN DE CONEXIËN HIDRAULICA", "unit": "PIEZA"}, {"id": "MFU000557", "desc": "4026684   EMPAQUE DE CARTER", "unit": "PIEZA"}, {"id": "MFU000558", "desc": "G251601   MARCADOR DE PRESION DE ACEITE", "unit": "PIEZA"}, {"id": "MFU000559", "desc": "8E7842   ARNES DE CONTROL DE TRANSMISION", "unit": "PIEZA"}, {"id": "MFU000560", "desc": "18K579   MANGUERA DE AGUA", "unit": "PIEZA"}, {"id": "MFU000561", "desc": "3787640   CONDENSERGP", "unit": "PIEZA"}, {"id": "MFU000562", "desc": "SP7669   TORNILLO CAT", "unit": "PIEZA"}, {"id": "MFU000563", "desc": "7G3834   CLIP CATERPILLAR", "unit": "PIEZA"}, {"id": "MFU000564", "desc": "6K2430   SEAL", "unit": "PIEZA"}, {"id": "MFU000565", "desc": "1234003 SEAL LIP TYPE", "unit": "PIEZA"}, {"id": "MFU000566", "desc": "5H3701   SCREW", "unit": "PIEZA"}, {"id": "MFU000567", "desc": "6B6682 NUT", "unit": "PIEZA"}, {"id": "MFU000568", "desc": "2R0239 SEAL O RING", "unit": "PIEZA"}, {"id": "MFU000569", "desc": "8P4994 WASHER", "unit": "PIEZA"}, {"id": "MFU000570", "desc": "8D2714 SEAL O RING", "unit": "PIEZA"}, {"id": "MFU000571", "desc": "1099437   ARANDELA 12MM", "unit": "PIEZA"}, {"id": "MFU000572", "desc": "3222188131   FILTRO AIRE EPIROC PRIMARIO", "unit": "PIEZA"}, {"id": "MFU000573", "desc": "3222188134   FILTRO AIRE EPIROC SECUNDARIO", "unit": "PIEZA"}, {"id": "MFU000574", "desc": "742330038802   FILTRO AIRE P532506", "unit": "PIEZA"}, {"id": "MFU000575", "desc": "PA2457   FILTRO AIRE PA2457", "unit": "PIEZA"}, {"id": "MFU000576", "desc": "5142420098   FILTRO AIRE RS3511 BALDWIN", "unit": "PIEZA"}, {"id": "MFU000577", "desc": "742330044513   FILTRO ACEITE P554005", "unit": "PIEZA"}, {"id": "MFU000578", "desc": "6060005692   FILTRO COMBUSTIBLE EPIROC", "unit": "PIEZA"}, {"id": "MFU000579", "desc": "7502000489937   FILTRO COMBUSTIBLE RFG026", "unit": "PIEZA"}, {"id": "MFU000580", "desc": "P555461   FILTRO HIDRAULICO P555461", "unit": "PIEZA"}, {"id": "MFU000581", "desc": "742330978597   FILTRO HIDRAULICO P574617", "unit": "PIEZA"}, {"id": "MFU000582", "desc": "791440001152   FILTRO HIDRAULICO PT90MPG", "unit": "PIEZA"}, {"id": "MFU000583", "desc": "PT9414   FILTRO HIDRAULICO PT9414", "unit": "PIEZA"}, {"id": "MFU000584", "desc": "742330174432   FILTRO ACEITE P550779", "unit": "PIEZA"}, {"id": "MFU000585", "desc": "742330087244   FILTRO ACEITE P551311", "unit": "PIEZA"}, {"id": "MFU000586", "desc": "791440066441   FILTRO COMBUSTIBLE BF7674D", "unit": "PIEZA"}, {"id": "MFU000587", "desc": "742330194850   FILTRO COMBUSTIBLE P551425", "unit": "PIEZA"}, {"id": "MFU000588", "desc": "742330194904   FILTRO COMBUSTIBLE P551430", "unit": "PIEZA"}, {"id": "MFU000589", "desc": "742330144374   FILTRO COMBUSTIBLE P552200", "unit": "PIEZA"}, {"id": "MFU000590", "desc": "742330044704   FILTRO COMBUSTIBLE P554620", "unit": "PIEZA"}, {"id": "MFU000591", "desc": "742330144206   FILTRO DE COMBUSTIBLE P550625", "unit": "PIEZA"}, {"id": "MFU000592", "desc": "742330044575   FILTRO REFRIGERANTE P554071 A", "unit": "PIEZA"}, {"id": "MFU000593", "desc": "742330201800   FILTRO SEPARADOR DE AGUA P551010", "unit": "PIEZA"}, {"id": "MFU000594", "desc": "765809570825   FILTRO ACEITE 57082", "unit": "PIEZA"}, {"id": "MFU000595", "desc": "791440058262   FILTRO ACEITE B5087", "unit": "PIEZA"}, {"id": "MFU000596", "desc": "76333117838   FILTRO ACEITE TL10241", "unit": "PIEZA"}, {"id": "MFU000597", "desc": "120291   FILTRO COMBUSTIBLE FF245", "unit": "PIEZA"}, {"id": "MFU000598", "desc": "7500556084620   FILTRO COMBUSTIBLE FF251", "unit": "PIEZA"}, {"id": "MFU000599", "desc": "1PFF5776   FILTRO COMBUSTIBLE FF5776", "unit": "PIEZA"}, {"id": "MFU000600", "desc": "791440000131   FILTRO COMBUSTIBLE PF10", "unit": "PIEZA"}, {"id": "MFU000601", "desc": "791440090682   FILTRO COMBUSTIBLE PF9870", "unit": "PIEZA"}, {"id": "MFU000602", "desc": "8231044410   FILTRO HIDRAULICO ATLAS COPCO", "unit": "PIEZA"}, {"id": "MFU000603", "desc": "68010   JUEGO DE FILTRO Y EMPAQUE JT211AC", "unit": "PIEZA"}, {"id": "MFU000604", "desc": "9100381019   FILTRO ACEITE FRAMPH3614", "unit": "PIEZA"}, {"id": "MFU000605", "desc": "76333117708   FILTRO ACEITE TL14670", "unit": "PIEZA"}, {"id": "MFU000606", "desc": "2037017   FILTRO COMBUSTIBLE F11140", "unit": "PIEZA"}, {"id": "MFU000607", "desc": "2346766   FILTRO COMBUSTIBLE FC1806", "unit": "PIEZA"}, {"id": "MFU000608", "desc": "744926070036   FILTRO COMBUSTIBLE GONHER GG5", "unit": "PIEZA"}, {"id": "MFU000609", "desc": "765809333956   FILTRO COMBUSTIBLE WIX 33395", "unit": "PIEZA"}, {"id": "MFU000610", "desc": "2048197   FILTRO DE COMBUSTIBLE FC1807", "unit": "PIEZA"}, {"id": "MFU000611", "desc": "742330038796   FILTRO AIRE P532505", "unit": "PIEZA"}, {"id": "MFU000612", "desc": "3203824   FILTRO AIRE P611190", "unit": "PIEZA"}, {"id": "MFU000613", "desc": "SA9540   FILTRO AIRE SA9540", "unit": "PIEZA"}, {"id": "MFU000614", "desc": "121523V2   FILTRO AIRE WIX 46671", "unit": "PIEZA"}, {"id": "MFU000615", "desc": "49976   FILTRO AIRE WIX 49976", "unit": "PIEZA"}, {"id": "MFU000616", "desc": "1202849600ED2   FILTRO ACEITE ATLAS COPCO", "unit": "PIEZA"}, {"id": "MFU000617", "desc": "8997879207734   FILTRO ACEITE C2906", "unit": "PIEZA"}, {"id": "MFU000618", "desc": "744926020338   FILTRO ACEITE GP31", "unit": "PIEZA"}, {"id": "MFU000619", "desc": "16VFLTGR   FILTRO ACEITE LF14000NN", "unit": "PIEZA"}, {"id": "MFU000620", "desc": "P550484   FILTRO ACEITE P550484", "unit": "PIEZA"}, {"id": "MFU000621", "desc": "742330044094   FILTRO DE ACEITE P552100", "unit": "PIEZA"}, {"id": "MFU000622", "desc": "742330111031   FILTRO DE ACEITE P559000", "unit": "PIEZA"}, {"id": "MFU000623", "desc": "791440077324   FILTRO ACEITE B7322", "unit": "PIEZA"}, {"id": "MFU000624", "desc": "791440038059   FILTRO ACEITE BT305", "unit": "PIEZA"}, {"id": "MFU000625", "desc": "791440042629   FILTRO ACEITE BT8845", "unit": "PIEZA"}, {"id": "MFU000626", "desc": "791440046511   FILTRO ACEITE BT8873 A", "unit": "PIEZA"}, {"id": "MFU000627", "desc": "9100046635   FILTRO ACEITE CH9911", "unit": "PIEZA"}, {"id": "MFU000628", "desc": "1PLF3349   FILTRO ACEITE LF3349", "unit": "PIEZA"}, {"id": "MFU000629", "desc": "791440060517   FILTRO COMBUSTIBLE BF7717", "unit": "PIEZA"}, {"id": "MFU000630", "desc": "791440079151   FILTRO COMBUSTIBLE BF7927", "unit": "PIEZA"}, {"id": "MFU000631", "desc": "CH111651   FILTRO DE ACEITE", "unit": "PIEZA"}, {"id": "MFU000632", "desc": "NE68902   FILTRO DE COMBUSTIBLE C/ CARCAZA", "unit": "PIEZA"}, {"id": "MFU000633", "desc": "FF0925030   FILTRO COMBUSTIBLE", "unit": "PIEZA"}, {"id": "MFU000634", "desc": "FF0925030   FILTRO COMBUSTIBLE 77008741", "unit": "PIEZA"}, {"id": "MFU000635", "desc": "744926020109   FILTRO COMBUSTIBLE GP11", "unit": "PIEZA"}, {"id": "MFU000636", "desc": "P550463   FILTRO COMBUSTIBLE P550463", "unit": "PIEZA"}, {"id": "MFU000637", "desc": "742330112267   FILTRO COMBUSTIBLE P550467", "unit": "PIEZA"}, {"id": "MFU000638", "desc": "742330016190   FILTRO HIDRAULICO P164381", "unit": "PIEZA"}, {"id": "MFU000639", "desc": "6262308332   FILTRO HIDRAULICO PT91", "unit": "PIEZA"}, {"id": "MFU000640", "desc": "68011   FILTRO TRANSMISION AUT JT211SOC", "unit": "PIEZA"}, {"id": "MFU000641", "desc": "765809469303   FILTRO AIRE 46930", "unit": "PIEZA"}, {"id": "MFU000642", "desc": "744926137265   FILTRO AIRE GA240", "unit": "PIEZA"}, {"id": "MFU000643", "desc": "76333607209   FILTRO AIRE RAM", "unit": "PIEZA"}, {"id": "MFU000644", "desc": "76333195072   FILTRO DE CABINA C25858", "unit": "PIEZA"}, {"id": "MFU000645", "desc": "765809290884   FILTRO DE CABINA WP2094", "unit": "PIEZA"}, {"id": "MFU000646", "desc": "638217138454   FILTRO DE COMBUSTIBLE FF5624", "unit": "PIEZA"}, {"id": "MFU000647", "desc": "765809338128   FILTRO SEPARADOR 33812", "unit": "PIEZA"}, {"id": "MFU000648", "desc": "765809310445   FILTRO SEPARADOR WF10249", "unit": "PIEZA"}, {"id": "MFU000649", "desc": "8997879016589   FILTRO AIRE A1864", "unit": "PIEZA"}, {"id": "MFU000650", "desc": "742330049051   FILTRO AIRE P827653", "unit": "PIEZA"}, {"id": "MFU000651", "desc": "791440094680   FILTRO AIRE RS5783", "unit": "PIEZA"}, {"id": "MFU000652", "desc": "11724N1   FILTRO AIRE WIX 42222", "unit": "PIEZA"}, {"id": "MFU000653", "desc": "120357   FILTRO COMBUSTIBLE FF248", "unit": "PIEZA"}, {"id": "MFU000654", "desc": "77794282   FILTRO HIDRAULICO 77794282", "unit": "PIEZA"}, {"id": "MFU000655", "desc": "E620132443   FILTRO DE ACEITE KIOTI", "unit": "PIEZA"}, {"id": "MFU000656", "desc": "T571038031   FILTRO HIDRAULICO KIOTI", "unit": "PIEZA"}, {"id": "MFU000657", "desc": "PK301025   PERNO KIOTI C/ SEGURO", "unit": "PIEZA"}, {"id": "MFU000658", "desc": "742330025529   FILTRO AIRE P181052", "unit": "PIEZA"}, {"id": "MFU000659", "desc": "80123   FILTRO AIRE PA1667FN", "unit": "PIEZA"}, {"id": "MFU000660", "desc": "FF448 FILTRO P/ GASOLINA", "unit": "PIEZA"}, {"id": "MFU000661", "desc": "DT17115   DETERGENTE LIQUIDO GARRAFA", "unit": "PIEZA"}, {"id": "MFU000662", "desc": "140008   LIMPIADOR MULTIUSOS", "unit": "PIEZA"}, {"id": "MFU000663", "desc": "660731807660   CERRADURA DE PASADOR", "unit": "PIEZA"}, {"id": "MFU000664", "desc": "CTAR092025   CINTA AISLANTE ROJA", "unit": "PIEZA"}, {"id": "MFU000665", "desc": "7501206651292   CINTA ANTIDERRAPANTE 12532", "unit": "PIEZA"}, {"id": "MFU000666", "desc": "CH271025   CINTA DE VINIL", "unit": "PIEZA"}, {"id": "MFU000667", "desc": "1452000   CONEXION DE ACEITE", "unit": "PIEZA"}, {"id": "MFU000668", "desc": "P120   LIJA PARA FIERRO GRADO 120", "unit": "PIEZA"}, {"id": "MFU000669", "desc": "7501206699690   REMACHES DE 1/8", "unit": "PIEZA"}, {"id": "MFU000670", "desc": "639277979858   WIRE SET TOOL BENCH", "unit": "PIEZA"}, {"id": "MFU000671", "desc": "7503050915834   BROCHA DE 3", "unit": "PIEZA"}, {"id": "MFU000672", "desc": "BSG11092025   JUEGO DE BISAGRA TUBULAR", "unit": "PIEZA"}, {"id": "MFU000673", "desc": "1805   LIJA PARA FIERRO GRADO 150", "unit": "PIEZA"}, {"id": "MFU000674", "desc": "939643   LOCTITE JUNTAS INSTANEAS", "unit": "PIEZA"}, {"id": "MFU000675", "desc": "89215103461   LUBRIPLATE GRASA DE ENSAMBLAJE", "unit": "PIEZA"}, {"id": "MFU000676", "desc": "404611092025   PLACA OVALADA C/ TORNILLOS P/ EXTRACTOR", "unit": "PIEZA"}, {"id": "MFU000677", "desc": "7501206622759   SOLDADURA C/ NUCLEO DE RESINA", "unit": "PIEZA"}, {"id": "MFU000678", "desc": "6290NX4   BOQUILLA DE CORTE 62904", "unit": "PIEZA"}, {"id": "MFU000679", "desc": "460485   BOQUILLA DE CORTE OXIACETILENO #4", "unit": "PIEZA"}, {"id": "MFU000680", "desc": "SC123#   BOQUILLA DE CORTE SC123#", "unit": "PIEZA"}, {"id": "MFU000681", "desc": "45242207510   CORTADORA ANULAR 5/8 X 1", "unit": "PIEZA"}, {"id": "MFU000682", "desc": "7506240623885   DISCO ABRASIVO DE 14", "unit": "PIEZA"}, {"id": "MFU000683", "desc": "799592764529   DISCO DE DESBASTE DE 4 1/2", "unit": "PIEZA"}, {"id": "MFU000684", "desc": "174419   DISCO DE LIJA DE 4 1/2", "unit": "PIEZA"}, {"id": "MFU000685", "desc": "7502215658739   PASTA P/ SOLDAR L26005", "unit": "PIEZA"}, {"id": "MFU000686", "desc": "11661   ROLLO DE LIJA P/ CIGUEÐAL", "unit": "PIEZA"}, {"id": "MFU000687", "desc": "F436 5/8   ARANDELA 5/8", "unit": "PIEZA"}, {"id": "MFU000688", "desc": "TOR5/8   TORNILLO 5/8", "unit": "PIEZA"}, {"id": "MFU000689", "desc": "M16X50   TORNILLO M16 X 50", "unit": "PIEZA"}, {"id": "MFU000690", "desc": "M20X50   TORNILLO M20 X 50", "unit": "PIEZA"}, {"id": "MFU000691", "desc": "11852RN   LLANTA PARA CARRETILLA", "unit": "PIEZA"}, {"id": "MFU000692", "desc": "PERNO DE SEGURIDAD P/ JALON", "unit": "PIEZA"}, {"id": "MFU000693", "desc": "TOPE DE 740", "unit": "PIEZA"}, {"id": "MFU000694", "desc": "CC160925178   CINCHO P/ CANALON", "unit": "PIEZA"}, {"id": "MFU000695", "desc": "SE0925013   SEÐALIZACION RUTA DE EVACUACIËN", "unit": "PIEZA"}, {"id": "MFU000696", "desc": "JA0925041   JALON DE BOLA TRIPLE", "unit": "PIEZA"}, {"id": "MFU000697", "desc": "CA0925040   ROLLO DE CABLE ACERADO", "unit": "PIEZA"}, {"id": "MFU000698", "desc": "47776   CODO CONDUIT 90░ 1\"", "unit": "PIEZA"}, {"id": "MFU000699", "desc": "CONEXIËN DE AIRE DE 1/4", "unit": "PIEZA"}, {"id": "MFU000700", "desc": "NG312   NIPLE GALVANIZADO 1/2 X 3", "unit": "PIEZA"}, {"id": "MFU000701", "desc": "NIPLE GALVANIZADO 1/2 X 8", "unit": "PIEZA"}, {"id": "MFU000702", "desc": "11005370   NIPLE GALVANIZADO DE 1/2 X 12", "unit": "PIEZA"}, {"id": "MFU000703", "desc": "NG12X6   NIPLE GALVANIZADO DE 1/2 X 6", "unit": "PIEZA"}, {"id": "MFU000704", "desc": "REDUCCION BUSHING DE 1 A 3/4", "unit": "PIEZA"}, {"id": "MFU000705", "desc": "REDUCCIËN BUSHING DE 1/2 A 1/4", "unit": "PIEZA"}, {"id": "MFU000706", "desc": "REDUCCIËN BUSHING DE 1/2 A 3/8", "unit": "PIEZA"}, {"id": "MFU000707", "desc": "REDUCCIËN BUSHING DE 3/4 A 1/2", "unit": "PIEZA"}, {"id": "MFU000708", "desc": "TAPON MACHO DE 2\"", "unit": "PIEZA"}, {"id": "MFU000709", "desc": "TEE GALVANIZADA 1/2", "unit": "PIEZA"}, {"id": "MFU000710", "desc": "77578013831   GUARDAPOLVO DE ALUMINIO Y VINILO", "unit": "PIEZA"}, {"id": "MFU000711", "desc": "14186   CARDA", "unit": "PIEZA"}, {"id": "MFU000712", "desc": "1/4NTP   JUEGO DE PISTOLA P/ AIRE", "unit": "PIEZA"}, {"id": "MFU000713", "desc": "49807300036   LIMPIADOR DE INYECTORES", "unit": "PIEZA"}, {"id": "MFU000714", "desc": "M250925238   MANIBELA DE PLASTICO", "unit": "PIEZA"}, {"id": "MFU000715", "desc": "170723   PROBADOR DE ANTICONGELANTE Y REFRIGERANTE", "unit": "PIEZA"}, {"id": "MFU000716", "desc": "F436 1/2   ARANDELA 1/2", "unit": "PIEZA"}, {"id": "MFU000717", "desc": "AP250925247   ARANDELA PLANA DE 1/2", "unit": "PIEZA"}, {"id": "MFU000718", "desc": "BA160925069   BOQUILLA DE MANGUERA DE AIRE DE 1/2", "unit": "PIEZA"}, {"id": "MFU000719", "desc": "BA160925068   BOQUILLA DE MANGUERA DE AIRE DE 3/4", "unit": "PIEZA"}, {"id": "MFU000720", "desc": "CDO250925235   CODO GALVANIZADO DE 1", "unit": "PIEZA"}, {"id": "MFU000721", "desc": "CG160925067   CODO GALVANIZADO DE 1/2", "unit": "PIEZA"}, {"id": "MFU000722", "desc": "47558   CODO GALVANIZADO DE 3/4", "unit": "PIEZA"}, {"id": "MFU000723", "desc": "30004   CODO NIPLE DE 1/2", "unit": "PIEZA"}, {"id": "MFU000724", "desc": "MF50816   CONEXIËN DIXON C/ TUERCA 3/8", "unit": "PIEZA"}, {"id": "MFU000725", "desc": "1X2PVC   COPLE DE PVC DE 1", "unit": "PIEZA"}, {"id": "MFU000726", "desc": "COPLE GALVANIZADO 1\"", "unit": "PIEZA"}, {"id": "MFU000727", "desc": "CG160925065   COPLE GALVANIZADO DE 1/2", "unit": "PIEZA"}, {"id": "MFU000728", "desc": "300401   COPLE GALVANIZADO DE 3/4", "unit": "PIEZA"}, {"id": "MFU000729", "desc": "GR250925244   GRILLETE DE 1/2 D", "unit": "PIEZA"}, {"id": "MFU000730", "desc": "IM250925240   INSERTO MINERO C/ TUERCA", "unit": "PIEZA"}, {"id": "MFU000731", "desc": "791279064168   LLAVE DE PASO DE 1", "unit": "PIEZA"}, {"id": "MFU000732", "desc": "LLAVE DE PASO DE 1/2", "unit": "PIEZA"}, {"id": "MFU000733", "desc": "40110   NIPLE 3/4 X 4", "unit": "PIEZA"}, {"id": "MFU000734", "desc": "NIPLE GALVANIZADO 1 X 4", "unit": "PIEZA"}, {"id": "MFU000735", "desc": "48825   NIPLE GALVANIZADO 3/4 X 12", "unit": "PIEZA"}, {"id": "MFU000736", "desc": "NP250925239   NIPLE GALVANIZADO DE 1", "unit": "PIEZA"}, {"id": "MFU000737", "desc": "47533   NIPLE GALVANIZADO DE 1 X 4", "unit": "PIEZA"}, {"id": "MFU000738", "desc": "73079299   NIPLE GALVANIZADO DE 3/4", "unit": "PIEZA"}, {"id": "MFU000739", "desc": "REDUCCION DE 3/4 A 1/2", "unit": "PIEZA"}, {"id": "MFU000740", "desc": "617852002436   TEE DE 20MM", "unit": "PIEZA"}, {"id": "MFU000741", "desc": "TEE1250925236   TEE GALVANIZADA DE 1", "unit": "PIEZA"}, {"id": "MFU000742", "desc": "TC58250925252   TUERCA DE SEGURIDAD 5/8", "unit": "PIEZA"}, {"id": "MFU000743", "desc": "38A   CANDADO", "unit": "PIEZA"}, {"id": "MFU000744", "desc": "COPLE DE ACERO DE 3\"", "unit": "PIEZA"}, {"id": "MFU000745", "desc": "LM250925265   LIJA MANUAL", "unit": "PIEZA"}, {"id": "MFU000746", "desc": "13MM300PSI   MANGUERA HIDRAULICA ROJA 1/2", "unit": "PIEZA"}, {"id": "MFU000747", "desc": "7506069000294   MANGUERA P/ SANITARIO 1/2  7/8", "unit": "PIEZA"}, {"id": "MFU000748", "desc": "SP250925256   SOPORTES DE RADIADOR", "unit": "PIEZA"}, {"id": "MFU000749", "desc": "TUERCA DE 3/8", "unit": "PIEZA"}, {"id": "MFU000750", "desc": "EP12300925   ESPARRAGO DE 1/2", "unit": "PIEZA"}, {"id": "MFU000751", "desc": "ESPARRAGO DE 3/8", "unit": "PIEZA"}, {"id": "MFU000752", "desc": "EP58300925   ESPARRAGO DE 5/8 X 1", "unit": "PIEZA"}, {"id": "MFU000753", "desc": "792363668392   TANQUE P/ PINTURA", "unit": "PIEZA"}, {"id": "MFU000754", "desc": "H05RH2103M   MANGUERA P/ OXICORTE", "unit": "PIEZA"}, {"id": "MFU000755", "desc": "TRABATUERCAS P/ CAMION", "unit": "PIEZA"}, {"id": "MFU000756", "desc": "TRABATUERCAS P/ LIGEROS", "unit": "PIEZA"}, {"id": "MFU000757", "desc": "CKHG140P   ACCESORIOS DE HIDROLAVADORA (KIT)", "unit": "PIEZA"}, {"id": "MFU000758", "desc": "17195   PALA CAJUELERA", "unit": "PIEZA"}, {"id": "MFU000759", "desc": "130620   PALA INDUSTRIAL", "unit": "PIEZA"}, {"id": "MFU000760", "desc": "RNG0925042   ROLLO GARLOK 700L", "unit": "PIEZA"}, {"id": "MFU000761", "desc": "MRF0925043   ROLLO MEMBRANA DE REFUERZO", "unit": "PIEZA"}, {"id": "MFU000762", "desc": "174419   DISCO DE LIJA DE 4 1/2", "unit": "PIEZA"}, {"id": "MFU000763", "desc": "778 DISCO DE CORTE DE 4 1/2", "unit": "PIEZA"}, {"id": "MFU000764", "desc": "PASC8 PASADOR DE BARRA", "unit": "PIEZA"}, {"id": "MFU000765", "desc": "19400010 PIJA DE 1/2", "unit": "PIEZA"}, {"id": "MFU000766", "desc": "4643261 BISAGRA CUADRADA DE 3\"", "unit": "PIEZA"}, {"id": "MFU000767", "desc": "SEÐALIZACION DE ESTACIONAMIENTO", "unit": "PIEZA"}, {"id": "MFU000768", "desc": "PTT1033 TRABA TUERCAS P CAMION", "unit": "PIEZA"}, {"id": "MFU000769", "desc": "RIN 24.5", "unit": "PIEZA"}, {"id": "MFU000770", "desc": "ACP4 ABRAZADERA ACP 4\"", "unit": "PIEZA"}, {"id": "MFU000771", "desc": "1/4NTP   JUEGO DE PISTOLA P/ AIRE", "unit": "PIEZA"}, {"id": "MFU000772", "desc": "48221900 SET DE NAVAJAS P/ CUTTER", "unit": "PIEZA"}, {"id": "MFU000773", "desc": "25022005531 SELLADOR DE POLIURETANO", "unit": "PIEZA"}, {"id": "MFU000774", "desc": "E565505 LLAVE LATON P/ MANGUERA DE 1/2", "unit": "PIEZA"}, {"id": "MFU000775", "desc": "BISAGRA CUADRADA DE 4\"", "unit": "PIEZA"}, {"id": "MFU000776", "desc": "LLAVE ALLEN DIFERENTES MEDIDAS TALLER", "unit": "PIEZA"}, {"id": "MFU000777", "desc": "CAJAS DE HERRAMIENTA TALLER", "unit": "PIEZA"}, {"id": "MFU000778", "desc": "COPLE P/ TOMA DE AGUA DE 3\"", "unit": "PIEZA"}, {"id": "MFU000779", "desc": "44647 PIJAS PUNTA DE BROCA (BOLSA)", "unit": "PIEZA"}, {"id": "MFU000780", "desc": "PIJA 6.4 X 38MM (BOLSA)", "unit": "PIEZA"}, {"id": "MFU000781", "desc": "48324462 PUNTA HEXAGONAL EN CRUZ PARA TALADRO", "unit": "PIEZA"}, {"id": "MFU000782", "desc": "32838898X KIT P/ TOMA DE FUERZA CHELSEA", "unit": "PIEZA"}, {"id": "MFU000783", "desc": "MX22946 PASADOR DE PUERTA MOD. 35", "unit": "PIEZA"}, {"id": "MFU000784", "desc": "11051617 PORTA FUSIBLE MEDIANO", "unit": "PIEZA"}, {"id": "MFU000785", "desc": "TAQUETE METALICO", "unit": "PIEZA"}, {"id": "MFU000786", "desc": "137701 ABRAZADERA DE 1/2", "unit": "PIEZA"}, {"id": "MFU000787", "desc": "DT1810 SOPORTE TRASERO P/ MOTOR", "unit": "PIEZA"}, {"id": "MFU000788", "desc": "7501087561314 ARRANCADOR", "unit": "PIEZA"}, {"id": "MFU000789", "desc": "CALZA NEGRA P/ LIGEROS", "unit": "PIEZA"}, {"id": "MFU000790", "desc": "2806800 MARCHA P/ CAMION NUEVA", "unit": "PIEZA"}, {"id": "MFU000791", "desc": "MLREF200WSMD REFLECTOR LED 200 WATTS", "unit": "PIEZA"}, {"id": "MFU000792", "desc": "B61403K LAMINA DE 41 X 1 1/2", "unit": "PIEZA"}, {"id": "MFU000793", "desc": "Q23144 KIT DE SOPORTES DE MOTOR", "unit": "PIEZA"}, {"id": "MFU000794", "desc": "ALMOHADILLA DE LIJADO", "unit": "PIEZA"}, {"id": "MFU000795", "desc": "BASE P/ EXTINTOR", "unit": "PIEZA"}, {"id": "MFU000796", "desc": "3544934C5   CONTROL PUERTA INTERNATIONAL 4300 3544934C5", "unit": "PIEZA"}, {"id": "MFU000797", "desc": "3896642   BALANCIN DE MOTOR CUMMINS", "unit": "PIEZA"}, {"id": "MFU000798", "desc": "23623188   ROCKER ARM", "unit": "PIEZA"}, {"id": "MFU000799", "desc": "23534738   ROCKER ARM", "unit": "PIEZA"}, {"id": "MFU000800", "desc": "B003336024244   CAB CONTROL MODULE 3579251C2", "unit": "PIEZA"}, {"id": "MFU000801", "desc": "3165142948584   PUNTA DE INYECTOR", "unit": "PIEZA"}, {"id": "MFU000802", "desc": "20395929   BRACKET VOLVOINTERNATIONAL", "unit": "PIEZA"}, {"id": "MFU000803", "desc": "880224   MOUNTING SUPPORT", "unit": "PIEZA"}, {"id": "MFU000804", "desc": "U323097303   GANCHO DE ARRASTRE KIOTI", "unit": "PIEZA"}, {"id": "MFU000805", "desc": "691315   GANCHO DE REMOLQUE", "unit": "PIEZA"}, {"id": "MFU000806", "desc": "2V7053   PUNTA DE COMPACTADOR", "unit": "PIEZA"}, {"id": "MFU000807", "desc": "3041042   TOMA DE FUERZA ENGRANE COMPRESOR CUMMINS", "unit": "PIEZA"}, {"id": "MFU000808", "desc": "AR69M24   TURBO AR69M24", "unit": "PIEZA"}, {"id": "MFU000809", "desc": "M190925218   MARCHA DE RAM PIPA DIESEL", "unit": "PIEZA"}, {"id": "MFU000810", "desc": "1350022   MARCHA JOHN DEERE", "unit": "PIEZA"}, {"id": "MFU000811", "desc": "QSL9190925215   MARCHA MOTOR QSL9", "unit": "PIEZA"}, {"id": "MFU000812", "desc": "UPVP2200N   BOMBA DE VAC═O", "unit": "PIEZA"}, {"id": "MFU000813", "desc": "11R0989   ECM CAB Y TRANSMISION", "unit": "PIEZA"}, {"id": "MFU000814", "desc": "2170320   HOMBRERA PARA PUERTA DE CABINA", "unit": "PIEZA"}, {"id": "MFU000815", "desc": "CHS17111   CAJA DE HERRAMIENTA SANY", "unit": "PIEZA"}, {"id": "MFU000816", "desc": "MN17113   MANOMETRO PARA NITROGENO", "unit": "PIEZA"}, {"id": "MFU000817", "desc": "CHK17112   VAJA DE HERRAMIENTA KIOTI", "unit": "PIEZA"}, {"id": "MFU000818", "desc": "850026973464   KIT DE TUBING P/ INSTALACIONES ELECTRICAS", "unit": "PIEZA"}, {"id": "MFU000819", "desc": "MN17114   MANOMETRO DOBLE P/ CARGA DE NITROGENO", "unit": "PIEZA"}, {"id": "MFU000820", "desc": "179252018415   TANQUE DE NITROGENO", "unit": "PIEZA"}, {"id": "MFU000821", "desc": "CAJA DE HERRAMIENTA SANY", "unit": "PIEZA"}, {"id": "MFU000822", "desc": "LLANTA 245/75 R16 ALL TERRAIN  ( MF090007 )", "unit": "PIEZA"}, {"id": "MFU000823", "desc": "265/65 R17   LLANTA 265/65 R17", "unit": "PIEZA"}, {"id": "MFU000824", "desc": "ASIENTO DE CV 8600 REPARADO", "unit": "PIEZA"}, {"id": "MFU000825", "desc": "ENFRIADOR USADO", "unit": "PIEZA"}, {"id": "MFU000826", "desc": "EA250925279   ENFRIADOR DE ACEITE HILUX", "unit": "PIEZA"}, {"id": "MFU000827", "desc": "TUBO DE INYECCIËN DE CONCRETO", "unit": "PIEZA"}, {"id": "MFU000828", "desc": "31508798625   MOTORCRAFT UREA GARRAFA", "unit": "PIEZA"}, {"id": "MFU000829", "desc": "SE7000   SOLVENTE DIELECTRICO GARRAFA", "unit": "PIEZA"}, {"id": "MFU000830", "desc": "SDM65B   CARRETE P/ MANGUERA", "unit": "PIEZA"}, {"id": "MFU000831", "desc": "951110191   DEPOSITO DE GRASA", "unit": "PIEZA"}, {"id": "MFU000832", "desc": "ESPIRAL DE 1/2", "unit": "PIEZA"}, {"id": "MFU000833", "desc": "51471802   PLATE U BOLT", "unit": "PIEZA"}, {"id": "MFU000834", "desc": "1549658   TAPA DE MANDO CAT", "unit": "PIEZA"}, {"id": "MFU000835", "desc": "20206   ARCO P/ SEGUETA", "unit": "PIEZA"}, {"id": "MFU000836", "desc": "1869180   COLLET CAT  DE 60MM", "unit": "PIEZA"}, {"id": "MFU000837", "desc": "AT438093   FLECHA CARDAN 16\" LARGO", "unit": "PIEZA"}, {"id": "MFU000838", "desc": "5007260   FLECHA CARDAN C/ YUGO Y CRUCETAS", "unit": "PIEZA"}, {"id": "MFU000839", "desc": "S024064   FLECHA DE 30\"", "unit": "PIEZA"}, {"id": "MFU000840", "desc": "S024065   FLECHA DE 30\" C/ CRUCETAS", "unit": "PIEZA"}, {"id": "MFU000841", "desc": "GV2815   GAVILAN 28 DIENTES 15\" LARGO", "unit": "PIEZA"}, {"id": "MFU000842", "desc": "RN0361120   MOTOR DE ROTACIËN H200", "unit": "PIEZA"}, {"id": "MFU000843", "desc": "38014333   MOTOR ELECTRICO", "unit": "PIEZA"}, {"id": "MFU000844", "desc": "1869185   PERNO CAT", "unit": "PIEZA"}, {"id": "MFU000845", "desc": "PORTA GAVILAN", "unit": "PIEZA"}, {"id": "MFU000846", "desc": "34510   SOPORTE TRASERO MOTOR CAMION", "unit": "PIEZA"}, {"id": "MFU000847", "desc": "2361511   TROMPA DE PERFORADORA H200", "unit": "PIEZA"}, {"id": "MFU000848", "desc": "93063311300532   VALVULA DE MARIPOSA C/ ACTUADOR", "unit": "PIEZA"}, {"id": "MFU000849", "desc": "Y164   YUGO 16 DIENTES 4\" ANCHO", "unit": "PIEZA"}, {"id": "MFU000850", "desc": "Y165   YUGO 16 DIENTES 5\" ANCHO", "unit": "PIEZA"}, {"id": "MFU000851", "desc": "MDU404   YUGO 33 DIENTES 3\" ANCHO", "unit": "PIEZA"}, {"id": "MFU000852", "desc": "Y3445   YUGO 34 DIENTES 4 1/2\" ANCHO", "unit": "PIEZA"}, {"id": "MFU000853", "desc": "Y3835   YUGO 38 DIENTES Y 3 1/2 ANCHO", "unit": "PIEZA"}, {"id": "MFU000854", "desc": "302025300   YUGO 45 DIENTES 6\" ANCHO MACHO", "unit": "PIEZA"}, {"id": "MFU000855", "desc": "Y394CAT   YUGO CAT C/ CRUCETA 39 DIENTES 4\" ANCHO", "unit": "PIEZA"}, {"id": "MFU000856", "desc": "A0827   YUGO DE 20 DIENTES", "unit": "PIEZA"}, {"id": "MFU000857", "desc": "Y3446   YUGO DE 34 DIENTES C/ BALERO COLGANTE", "unit": "PIEZA"}, {"id": "MFU000858", "desc": "FC250925276   FLECHA CAMION 49\"", "unit": "PIEZA"}, {"id": "MFU000859", "desc": "1530366 COMPRESORT DE AIRE ISM USADO", "unit": "PIEZA"}, {"id": "MFU000860", "desc": "3090942 BOMBA DE DIESEL", "unit": "PIEZA"}, {"id": "MFU000861", "desc": "EJE DELATERO HILUX", "unit": "PIEZA"}, {"id": "MFU000862", "desc": "PUNTA HOMOCINETICA", "unit": "PIEZA"}, {"id": "MFU000863", "desc": "26509688 SLIDE PLATE (USADO)", "unit": "PIEZA"}, {"id": "MFU000864", "desc": "TRASNMISION FORD F-550 USADA", "unit": "PIEZA"}, {"id": "MFU000865", "desc": "24570195DSRS01 LLANTA 245/70 R19.5 DIRECCION", "unit": "PIEZA"}, {"id": "MFU000866", "desc": "SMT5531785 LLANTA 245/70 R19.5 TRACCION", "unit": "PIEZA"}, {"id": "MFU000867", "desc": "1601850 HIDROLAVADORA ELECTRICA ALTO DESEMPEÐO 1800 PSI", "unit": "PIEZA"}, {"id": "MFU000868", "desc": "ASP06N ASPIRADORA TRUPER 6 GAL", "unit": "PIEZA"}, {"id": "MFU000869", "desc": "9710215 EXTENSION DE USO RUDO 10 MTS", "unit": "PIEZA"}, {"id": "MFU000870", "desc": "PA3596 FILTRO ADMISIËN RANGER 2021", "unit": "PIEZA"}, {"id": "MFU000871", "desc": "10W-30 ACEITE MOTOR X LTS", "unit": "PIEZA"}, {"id": "MFU000872", "desc": "MKD2216 JUEGO DE BALATAS DELANTERAS RANGER 2021", "unit": "PIEZA"}, {"id": "MFU000873", "desc": "D1911 JUEGO BALATAS DELANTERAS NISSAN", "unit": "PIEZA"}, {"id": "MFU000874", "desc": "LUBRI PLATE GRASA DE ENSAMBLAJE", "unit": "LT"}, {"id": "MFU000875", "desc": "LIJA RUEDA FLAP DE 3\"", "unit": "PIEZA"}, {"id": "MFU000876", "desc": "ASIENTO CON TAPA PARA WC", "unit": "PIEZA"}, {"id": "MFU000877", "desc": "PINZA ABRE CANDADOS", "unit": "PIEZA"}, {"id": "MFU000878", "desc": "RASH DE 3/8\"", "unit": "PIEZA"}, {"id": "MFU000879", "desc": "CLAVIJA MACHO PARA EXTENSION ELECTRICA", "unit": "PIEZA"}, {"id": "MFU000880", "desc": "ADAPTADOR DE 1/2 A 3/4 PARA PISTOLA", "unit": "PIEZA"}, {"id": "MFU000881", "desc": "LIBRETA DE APUNTES PASTA DURA DE RAYA", "unit": "PIEZA"}, {"id": "MFU000882", "desc": "BOTA DE SEGURIDAD TALLA 5", "unit": "PAR"}, {"id": "MFU000883", "desc": "ARANDELA ESTRUCTURAL DE 1/2", "unit": "PIEZA"}, {"id": "MFU000884", "desc": "ARANDELA ESTRUCTURAL 3/8", "unit": "PIEZA"}, {"id": "MFU000885", "desc": "ARANDELA ESTRUCTURAL 9/16", "unit": "PIEZA"}, {"id": "MFU000886", "desc": "ARANDELA ESTRUCTURAL M10", "unit": "PIEZA"}, {"id": "MFU000887", "desc": "TORNILLO PARA COLLET", "unit": "PIEZA"}, {"id": "MFU000888", "desc": "EJE PARA SCOOP TRAM USADO", "unit": "PIEZA"}, {"id": "MFU000889", "desc": "CLUSTER USADO", "unit": "PIEZA"}, {"id": "MFU000890", "desc": "MANIJA DE PUERTA USADA", "unit": "PIEZA"}, {"id": "MFU000891", "desc": "GUARDAS USADAS", "unit": "PIEZA"}, {"id": "MFU000892", "desc": "BASE P/ HOMBRERA CAT USADA", "unit": "PIEZA"}, {"id": "MFU000893", "desc": "PERNO USADO ANCLADOR RESEMIN", "unit": "PIEZA"}, {"id": "MFU000894", "desc": "7N1639 BASE DE RADIADOR CAT USADA", "unit": "PIEZA"}, {"id": "MFU000895", "desc": "TAPA USADA", "unit": "PIEZA"}, {"id": "MFU000896", "desc": "BUJES USADOS DIFERENTES MEDIDAS", "unit": "PIEZA"}, {"id": "MFU000897", "desc": "REDUCCIËN BUSHING USADA DE 2 A 1", "unit": "PIEZA"}, {"id": "MFU000898", "desc": "TARRAJA USADA M20 X 1.5", "unit": "PIEZA"}, {"id": "MFU000899", "desc": "VALVULA HIDRAULICA USADA", "unit": "PIEZA"}, {"id": "MFU000900", "desc": "1P4579 BRIDA DIVIDIDA 61MM USADA", "unit": "PIEZA"}, {"id": "MFU000901", "desc": "RETAINER CAT USADO", "unit": "PIEZA"}, {"id": "MFU000902", "desc": "TUERCA CAT USADA", "unit": "PIEZA"}, {"id": "MFU000903", "desc": "SPANDING SHAFT RESEMIN 8 1/2\" USADO", "unit": "PIEZA"}, {"id": "MFU000904", "desc": "SPANDING SHAFT RESEMIN 6\" USADO", "unit": "PIEZA"}, {"id": "MFU000905", "desc": "PLACA CUADRADA CAT USADA", "unit": "PIEZA"}, {"id": "MFU000906", "desc": "TAPA CAT USADA", "unit": "PIEZA"}, {"id": "MFU000907", "desc": "GUARDA SANDVIK USADA", "unit": "PIEZA"}, {"id": "MFU000908", "desc": "4458876 RASCADOR DE ACERO CAT USADO", "unit": "PIEZA"}, {"id": "MFU000909", "desc": "ARANDELA USADA", "unit": "PIEZA"}, {"id": "MFU000910", "desc": "CONEXIËN HIDRAULICA C/ BASE USADA", "unit": "PIEZA"}, {"id": "MFU000911", "desc": "RODAMIENTO SANDVIK USADO", "unit": "PIEZA"}, {"id": "MFU000912", "desc": "PERNOS SANDVIK USADOS", "unit": "PIEZA"}, {"id": "MFU000913", "desc": "32118818D CROSS PIECE SANDVIK USADA", "unit": "PIEZA"}, {"id": "MFU000914", "desc": "55002012 SWING PIECE SANDVIK USADA", "unit": "PIEZA"}, {"id": "MFU000915", "desc": "55002381 BOOM HEAD SANDVIK USADO", "unit": "PIEZA"}, {"id": "MFU000916", "desc": "CABLE DE RETROCESO USADO", "unit": "PIEZA"}, {"id": "MFU000917", "desc": "ESPIGA USADA", "unit": "PIEZA"}, {"id": "MFU000918", "desc": "DESLIZADERA USADA DIFERENTES TAMAÐOS", "unit": "PIEZA"}, {"id": "MFU000919", "desc": "TAPA DE MOTOR USADA", "unit": "PIEZA"}, {"id": "MFU000920", "desc": "VALVULA HIDRAULICA SANDVIK USADA", "unit": "PIEZA"}, {"id": "MFU000921", "desc": "ABRAZADERA P/ MANGUERAS HIDRAULICAS", "unit": "PIEZA"}, {"id": "MFU000922", "desc": "HULE TOMA DE FILTRO DE AIRE USADO", "unit": "PIEZA"}, {"id": "MFU000923", "desc": "ANILLO RESEMIN USADO", "unit": "PIEZA"}, {"id": "MFU000924", "desc": "WLT006360QHYJM ACTUADOR HIDRAULICO RESEMIN USADO", "unit": "PIEZA"}, {"id": "MFU000925", "desc": "SOPORTE P/ PUERTA USADO", "unit": "PIEZA"}, {"id": "MFU000926", "desc": "PERNO RESEMIN RETRACTIL USADO", "unit": "PIEZA"}, {"id": "MFU000927", "desc": "CRUCETA CAT USADA", "unit": "PIEZA"}, {"id": "MFU000928", "desc": "3126910355 VALVULA SOLENOIDE USADA", "unit": "PIEZA"}, {"id": "MFU000929", "desc": "BRIDA DE ACERO 3\" USADA", "unit": "PIEZA"}, {"id": "MFU000930", "desc": "HORQUILLA DE SUSPENSION USADA", "unit": "PIEZA"}, {"id": "MFU000931", "desc": "POLEA DE BADA USADA", "unit": "PIEZA"}, {"id": "MFU000932", "desc": "JALON USADO", "unit": "PIEZA"}, {"id": "MFU000933", "desc": "P5100471 MARCHA JOHN DEERE USADA", "unit": "PIEZA"}, {"id": "MFU000934", "desc": "MARCHA DE JUMBO USADA", "unit": "PIEZA"}, {"id": "MFU000935", "desc": "MARCHA L200 USADA", "unit": "PIEZA"}, {"id": "MFU000936", "desc": "ALTERNADOR USADO LIGEROS", "unit": "PIEZA"}, {"id": "MFU000937", "desc": "CODO DE HIERRO CAT USADO", "unit": "PIEZA"}, {"id": "MFU000938", "desc": "01183618 ALTERNADOR MOTOR DEUTZ USADO", "unit": "PIEZA"}, {"id": "MFU000939", "desc": "1800A387 ALTERNADOR MITSUBISHI USADO", "unit": "PIEZA"}, {"id": "MFU000940", "desc": "22SI ALTERNADOR DELCO REMY USADO", "unit": "PIEZA"}, {"id": "MFU000941", "desc": "709TA11 COMPRESOR DE AIRE ACONDICIONADO USADO", "unit": "PIEZA"}, {"id": "MFU000942", "desc": "7H15 COMPRESOR DE AIRE ACONDICIONADO USADO", "unit": "PIEZA"}, {"id": "MFU000943", "desc": "MOTOR ELECTRICO EMERSON USADO", "unit": "PIEZA"}, {"id": "MFU000944", "desc": "7W242407 ALTERNADOR USADO C/ SOPORTE", "unit": "PIEZA"}, {"id": "MFU000945", "desc": "5669549 ALTERNADOR DE ST USADO", "unit": "PIEZA"}, {"id": "MFU000946", "desc": "2W8494 ALTERNADOR DE ST USADO", "unit": "PIEZA"}, {"id": "MFU000947", "desc": "24SI ALTERNADOR DELCO REMY USADO", "unit": "PIEZA"}, {"id": "MFU000948", "desc": "HRS178A VALVULA DE DIRECCION ST USADA", "unit": "PIEZA"}, {"id": "MFU000949", "desc": "HR2284A VALVULA DE DIRECCION ST USADA", "unit": "PIEZA"}, {"id": "MFU000950", "desc": "CABEZAL SANDVIK USADO", "unit": "PIEZA"}, {"id": "MFU000951", "desc": "PLACA DE 3/8 USADA", "unit": "PIEZA"}, {"id": "MFU000952", "desc": "BASE DE DESCANSA BRAZOS USADA", "unit": "PIEZA"}, {"id": "MFU000953", "desc": "TAPA DE ACEITE HIDRAULICO USADA", "unit": "PIEZA"}, {"id": "MFU000954", "desc": "TAPA DE GOMA USADA", "unit": "PIEZA"}, {"id": "MFU000955", "desc": "VALVULA HIDRAULICA MANUAL USADA", "unit": "PIEZA"}, {"id": "MFU000956", "desc": "GUARDA CILINDRICA DE ST USADA", "unit": "PIEZA"}, {"id": "MFU000957", "desc": "PLACA RECTANGULAR DE ST USADA", "unit": "PIEZA"}, {"id": "MFU000958", "desc": "GU═A SOPORTE DE CAMION USADO", "unit": "PIEZA"}, {"id": "MFU000959", "desc": "RIELES SANDVIK USADOS", "unit": "PIEZA"}, {"id": "MFU000960", "desc": "GU═A SANDVIK USADA", "unit": "PIEZA"}, {"id": "MFU000961", "desc": "JUNTA METALICA SANDVIK USADA", "unit": "PIEZA"}, {"id": "MFU000962", "desc": "CUERNO DE CILINDRO DE LEVANTE CAT USADO", "unit": "PIEZA"}, {"id": "MFU000963", "desc": "BASE DE CENTRALIZADOR USADA", "unit": "PIEZA"}, {"id": "MFU000964", "desc": "HORQUILLA SANDVIK USADA", "unit": "PIEZA"}, {"id": "MFU000965", "desc": "LEVER SANDVIK USADO", "unit": "PIEZA"}, {"id": "MFU000966", "desc": "LINEA DE COMBUSTIBLE CAT USADA", "unit": "PIEZA"}, {"id": "MFU000967", "desc": "997000630 KIT DE LUBRICACION RESEMIN", "unit": "PIEZA"}, {"id": "MFU000968", "desc": "TAPA DE CONEXIONES HIDRAULICAS RESEMIN", "unit": "PIEZA"}, {"id": "MFU000969", "desc": "BVLIP12BSS1N20 VALVULA DE ALTA PRESION USADA", "unit": "PIEZA"}, {"id": "MFU000970", "desc": "R900407515 CONTROL VALVE USADA", "unit": "PIEZA"}, {"id": "MFU000971", "desc": "040452007 VALVULA CONTRA BALANCE USADA", "unit": "PIEZA"}, {"id": "MFU000972", "desc": "B70425MH21 VALVULA DE CONTROL DE PRESION USADA", "unit": "PIEZA"}, {"id": "MFU000973", "desc": "VALVULA VOGEL USADA", "unit": "PIEZA"}, {"id": "MFU000974", "desc": "VALVULA DE ESCAPE USADA", "unit": "PIEZA"}, {"id": "MFU000975", "desc": "018F7397 BOBINA SOLENOIDE USADA", "unit": "PIEZA"}, {"id": "MFU000976", "desc": "2IG1AA VALVULA PILOTO USADA", "unit": "PIEZA"}, {"id": "MFU000977", "desc": "BPBM5 DISTRIBUIDOR PROGRESIVO", "unit": "PIEZA"}, {"id": "MFU000978", "desc": "PLACA RESEMIN USADA", "unit": "PIEZA"}, {"id": "MFU000979", "desc": "EMPAQUE DE MAZA USADO", "unit": "PIEZA"}, {"id": "MFU000980", "desc": "BUJE DE BRONCE DE 4\" USADO", "unit": "PIEZA"}, {"id": "MFU000981", "desc": "PLACA DE BONCE DE 6 X 6 1/2\" USADA", "unit": "PIEZA"}, {"id": "MFU000982", "desc": "PIN CLEVIS USADO", "unit": "PIEZA"}, {"id": "MFU000983", "desc": "BUJE DE HIERRO DE 4\" USADO", "unit": "PIEZA"}, {"id": "MFU000984", "desc": "CODO DE PLASTICO DE 1 1/2\" USADO", "unit": "PIEZA"}, {"id": "MFU000985", "desc": "CONEXIËN HIDRAULICA DE 2\" USADA", "unit": "PIEZA"}, {"id": "MFU000986", "desc": "CONEXIËN HIDRAULICA DE 1\" USADA", "unit": "PIEZA"}, {"id": "MFU000987", "desc": "PU107029RMXY POLEA DOBLE USADA", "unit": "PIEZA"}, {"id": "MFU000988", "desc": "VALVULA DE CILINDRO TENSOR USADO", "unit": "PIEZA"}, {"id": "MFU000989", "desc": "MANOMETRO DE PRESION DE ACEITE USADO", "unit": "PIEZA"}, {"id": "MFU000990", "desc": "3J9027 ANILLO GU═A CAT", "unit": "PIEZA"}, {"id": "MFU000991", "desc": "RET╔N USADO", "unit": "PIEZA"}, {"id": "MFU000992", "desc": "TOPE DE GOMA REDONDO USADO", "unit": "PIEZA"}, {"id": "MFU000993", "desc": "0348C0276 BOTON PUSH USADO", "unit": "PIEZA"}, {"id": "MFU000994", "desc": "INTERRUPTOR REDONDO LED USADO", "unit": "PIEZA"}, {"id": "MFU000995", "desc": "218524 MANOMETRO DIXON USADO", "unit": "PIEZA"}, {"id": "MFU000996", "desc": "PERNOS SANDVIK DIFERENTES MEDIDAS USADOS", "unit": "PIEZA"}, {"id": "MFU000997", "desc": "COLLETS SANDVIK DIFERENTES MEDIDAS USADOS", "unit": "PIEZA"}, {"id": "MFU000998", "desc": "TAPAS DE QUESOS SANDVIK USADAS", "unit": "PIEZA"}, {"id": "MFU000999", "desc": "3507555 INYECTOR CAT USADO", "unit": "PIEZA"}, {"id": "MFU001000", "desc": "1166403 INYECTOR CAT USADO", "unit": "PIEZA"}, {"id": "MFU001001", "desc": "1165917 INTECTOR CAT USADO", "unit": "PIEZA"}, {"id": "MFU001002", "desc": "1165417 INYECTOR CAT USADO", "unit": "PIEZA"}, {"id": "MFU001003", "desc": "2530618 INYECTOR CAT USADO", "unit": "PIEZA"}, {"id": "MFU001004", "desc": "1178585 INYECTOR CAT USADO", "unit": "PIEZA"}, {"id": "MFU001005", "desc": "2123460 INYECTOR CAT USADO", "unit": "PIEZA"}, {"id": "MFU001006", "desc": "4220894 INYECTOR REMAN USADO", "unit": "PIEZA"}, {"id": "MFU001007", "desc": "BASE P/ CALZA USADA", "unit": "PIEZA"}, {"id": "MFU001008", "desc": "BASE P/ PISTOLA DE COMBUSTIBLE USADA", "unit": "PIEZA"}, {"id": "MFU001009", "desc": "FUSIBLE DE CAMION USADO C/ BASE", "unit": "PIEZA"}, {"id": "MFU001010", "desc": "WMF14FE JUEGO DE BALATA DELANTERA USADO", "unit": "PIEZA"}, {"id": "MFU001011", "desc": "410047 BRIDA P/ MANGUERA USADA", "unit": "PIEZA"}, {"id": "MFU001012", "desc": "BUJE SOPORTE USADO", "unit": "PIEZA"}, {"id": "MFU001013", "desc": "ARANDELA PLANA USADA", "unit": "PIEZA"}, {"id": "MFU001014", "desc": "VARILLA P/ CLUTCH USADA", "unit": "PIEZA"}, {"id": "MFU001015", "desc": "ESCALON METALICO USADO", "unit": "PIEZA"}, {"id": "MFU001016", "desc": "P3103533RX MODULO ECM REMAN USADO", "unit": "PIEZA"}, {"id": "MFU001017", "desc": "B0DLBC36J4 REGULADOR DE PRESION DE AIRE", "unit": "PIEZA"}, {"id": "MFU001018", "desc": "C11001NL5 GASKET SET", "unit": "PIEZA"}, {"id": "MFU001019", "desc": "A4089998 LOWER GASKET SET", "unit": "PIEZA"}, {"id": "MFU001020", "desc": "BO250925263   BOTIQUIN", "unit": "PIEZA"}, {"id": "MFU001021", "desc": "LM250925261   LENTE DE MALLA", "unit": "PIEZA"}, {"id": "MFU001022", "desc": "LSO250925264   LENTE SEGURIDAD OSCURO", "unit": "PIEZA"}, {"id": "MFU001023", "desc": "CIL0925023   CILINDRO DE FRENOS HILUX C/ DEPOSITO", "unit": "PIEZA"}, {"id": "MFU001024", "desc": "TRH0925019 TIRANTES DE HILUX", "unit": "PIEZA"}, {"id": "MFU001025", "desc": "FHL2000925014   FLECHA HOMOCINETICA L200", "unit": "PIEZA"}, {"id": "MFU001026", "desc": "5020227   SOLENOIDE PARA MARCHA DENSO", "unit": "PIEZA"}, {"id": "MFU001027", "desc": "DK667134AV   ACEITE DE MOTOR SAE30", "unit": "PIEZA"}, {"id": "MFU001028", "desc": "52948715690   ACEITE DE TRANSMISION ESTANDAR", "unit": "PIEZA"}, {"id": "MFU001029", "desc": "31508822511   ACEITE P/ MOTOR 5W30", "unit": "PIEZA"}, {"id": "MFU001031", "desc": "122649   ACEITE ATF CUBETA", "unit": "PIEZA"}, {"id": "MFU001032", "desc": "7503024440782   ACEITE CAT TDTO30 CUBETA", "unit": "PIEZA"}, {"id": "MFU001033", "desc": "128116   ACEITE HD50", "unit": "PIEZA"}, {"id": "MFU001034", "desc": "122662   ACEITE HIDRAULICO 424", "unit": "PIEZA"}, {"id": "MFU001035", "desc": "TO430   ACEITE LUBRAL TO-4-30 CUBETA", "unit": "PIEZA"}, {"id": "MFU001036", "desc": "7501116200962   ACEITE MOBIL 15W40", "unit": "PIEZA"}, {"id": "MFU001037", "desc": "7503019361573   ACEITE MOBIL 85-140", "unit": "PIEZA"}, {"id": "MFU001038", "desc": "122664   ACEITE RARUS", "unit": "PIEZA"}, {"id": "MFU001039", "desc": "1082339   GRASA MULTIPLEX 220", "unit": "PIEZA"}, {"id": "MFU001040", "desc": "00390180   NEUMO ACEITE", "unit": "PIEZA"}, {"id": "MFU001041", "desc": "CC2847   ANTICONGELANTE GARRAFA", "unit": "PIEZA"}, {"id": "MFU001042", "desc": "10074804032113   BLUE DEF UREA", "unit": "PIEZA"}, {"id": "MFU001043", "desc": "FLECHA C/ MAZA TOYOTA", "unit": "PIEZA"}, {"id": "MFU001045", "desc": "1039527 CONDENSER GP REFRIGERANTE WITH FANS", "unit": "PIEZA"}, {"id": "MFU001046", "desc": "FLECHA DEL INTER/MOTRIZ MACHO Y HEMBRA CERRADA 21.5\", LADO HEMRA 16\" DE LARGO", "unit": "PIEZA"}, {"id": "MFU001047", "desc": "VOLANTE PARA TOYOTA HILUX USADO", "unit": "PIEZA"}, {"id": "MFU001048", "desc": "BOMBA DE AGUA ST REPARADA", "unit": "PIEZA"}, {"id": "MFU001049", "desc": "UNIDAD DE GIRO REPARADA (ROTARY ACTUATOR)", "unit": "PIEZA"}, {"id": "MFU001050", "desc": "BOMBA 100CC REPARADA", "unit": "PIEZA"}, {"id": "MFU001051", "desc": "MOTOR DE CAMION REPARADO", "unit": "PIEZA"}, {"id": "MFU001052", "desc": "1178584 PUMP GP (USADA)", "unit": "PIEZA"}, {"id": "MFU001053", "desc": "PERNO PARA RETRO", "unit": "PIEZA"}, {"id": "MFU001054", "desc": "PREFORADORA RD314 (REPARADA)", "unit": "PIEZA"}, {"id": "MFU001055", "desc": "PREFORADORA HLX5 (REPARADA)", "unit": "PIEZA"}, {"id": "MFU001056", "desc": "CILINDRO DE LEVANTE REPARADO SCOOP TRAM", "unit": "PIEZA"}, {"id": "MFU001057", "desc": "CILINDRO CAMBIO DE MAQUINAS REPARADO", "unit": "PIEZA"}, {"id": "MFU001058", "desc": "1180684 VOLANTE DEL MOTOR USADO", "unit": "PIEZA"}, {"id": "MFU001059", "desc": "4N2514 ENGRANAJE MINIMO DEL VOLANTE DE 444.99 MM USADO", "unit": "PIEZA"}, {"id": "MFU001060", "desc": "1T1863 ANILLO DE MANDO DE 72 DIENTES USADO", "unit": "PIEZA"}, {"id": "MFU001061", "desc": "TROMPA DE PERFORADORA HLX5/RDX5 USADA", "unit": "PIEZA"}, {"id": "MFU001062", "desc": "2912681 CILINDRO ESTABILIZADOR RETRO CAT 416  (REPARADO)", "unit": "PIEZA"}, {"id": "MFU00160", "desc": "CILINDRO DE LEVANTE DE CAJON PARA CV 8600 (REPARADO)", "unit": "PIEZA"}, {"id": "MFU00162", "desc": "3G2665 TAPON USADO", "unit": "PIEZA"}, {"id": "MFU00167", "desc": "BASTAGO P/SCOOP TRAM", "unit": "PIEZA"}, {"id": "MFU00865", "desc": "INYECTOR ST-22 USADO", "unit": "PIEZA"}, {"id": "MFU00866", "desc": "CILIUNDRO DE ANCLAJE JBO-10", "unit": "PIEZA"}, {"id": "MFUOTRO", "desc": "OTRO", "unit": "PIEZA"}]
